Workbook
Name FINISHES_NET_TOTAL: 'Finishes Cover'!$F$24
Name FINISHES_GRAND_TOTAL: 'Finishes Cover'!$F$30
Name ICF_PACKAGE_TOTAL: 'Finishes Cover'!$F$33
Name COMBINED_TOTAL: 'Finishes Cover'!$F$34

Sheet Cover
A10: BILL OF QUANTITIES
A11: ICF KIT · CONCRETE · LABOUR
A14: LAND TO REAR OF 1-8 WESLEY TERRACE, CASTLESIDE
A15: 18-Plot ICF Development · 8 blocks · Castleside, Consett, County Durham DH8 9QB
B17: Quotation Reference | C17: ES26-080
B18: Project | C18: Land to Rear of 1-8 Wesley Terrace, Castleside
B19: House Type | C19: HT01 3B5P (semi pairs + terraces of 3) / HT02 2B4P bungalow
B20: Client | C20: Wannop Developments Ltd
B21: Site Address | C21: Land to Rear of 1-8 Wesley Terrace, Castleside, Consett DH8 9QB
B22: BOQ Issued | C22: 19 October 2026
B23: BOQ Reference | C23: BOQ-ES26-080-001 · Revision 1.0
B24: Prepared by | C24: Tom Smith — BuildEase Manager, Nudura UK
B25: Issued by | C25: Tremco Construction Products Group
B26: Currency | C26: Pound Sterling (GBP) · VAT at 20%
B27: Measurement Convention | C27: RICS New Rules of Measurement (NRM2)
B29: IMPORTANT NOTICE — DISCLAIMER
B30: • This Bill of Quantities is supplied in good faith based on the BuildEase take-off models for Land to Rear of 1-8 Wesley Terrace, Castleside and the associated Tremco CPG quotation.
B31: • ALL QUANTITIES SHOULD BE INDEPENDENTLY CHECKED AND VERIFIED BY THE PROJECT QS / QUANTITY SURVEYOR before tender submission, ordering or contract award.
B32: • This BOQ does NOT include an external render / finish allowance. Any render, coatings or external wall finish must be measured and priced separately.
B33: • Section C (Concrete) volumes are geometric voids — allow ~3% web displacement deduction and ~5% wastage on top when ordering ready-mix.
B34: • Section D (Labour) day estimates are scaled proportionately from a reference project; actual gang productivity will vary with site conditions, weather and trade experience.
B35: • BuildEase, Tremco Construction Products Group and Nudura UK accept no liability for tender or contract outcomes arising from the use of these figures. If in doubt — ask.
B36: • Contact: Tom Smith — BuildEase Manager, Nudura UK — for clarification on any quantity or rate basis in this document.

Sheet Contents
A1: CONTENTS
A4: Section | B4: Description | C4: Sheet | D4: Status
B5: Cover & Project Information | C5: Cover
B6: Contents | C6: Contents
B7: Indicative Programme (Gantt) | C7: Programme | D7: Information
B8: Summary of Tender Pricing | C8: Summary
A9: A | B9: Preliminaries | C9: A_Preliminaries | D9: Contractor priced
A10: B | B10: ICF Kit Supply | C10: B_ICF_Supply | D10: Pre-priced
A11: C | B11: Concrete Supply, Pump & Placement | C11: C_Concrete | D11: Contractor priced
A12: D | B12: Labour — ICF, Floors & Roofs | C12: D_Labour | D12: Contractor priced
A13: F | B13: Reference Data (informative only) | C13: F_Reference | D13: —

Sheet Programme
A1: PROG · INDICATIVE INSTALL PROGRAMME — RESOURCE-LEVELLED, ONE COLUMN PER WORKING DAY
A2: Group-by-group sequential build with a staggered start between groups. ICF install + snag + pour cycles, intermediate floors and roof structure are completed before moving on. Resourcing and durations below are indicative and must be validated by site management. Render / external finish is NOT included in this programme.
F3: W1 | M3: W2 | T3: W3 | AA3: W4 | AH3: W5 | AO3: W6 | AV3: W7 | BC3: W8 | BJ3: W9 | BQ3: W10
A4: Group | B4: Plots | C4: Forms | D4: Weeks | E4: Start wk | F4: M | G4: T | H4: W | I4: T | J4: F | K4: S | L4: S | M4: M | N4: T | O4: W | P4: T | Q4: F | R4: S | S4: S | T4: M | U4: T | V4: W | W4: T | X4: F | Y4: S | Z4: S | AA4: M | AB4: T | AC4: W | AD4: T | AE4: F | AF4: S | AG4: S | AH4: M | AI4: T | AJ4: W | AK4: T | AL4: F | AM4: S | AN4: S | AO4: M | AP4: T | AQ4: W | AR4: T | AS4: F | AT4: S | AU4: S | AV4: M | AW4: T | AX4: W | AY4: T | AZ4: F | BA4: S | BB4: S | BC4: M | BD4: T | BE4: W | BF4: T | BG4: F | BH4: S | BI4: S | BJ4: M | BK4: T | BL4: W | BM4: T | BN4: F | BO4: S | BP4: S | BQ4: M | BR4: T | BS4: W | BT4: T | BU4: F | BV4: S | BW4: S
A5: Block B01 - HT01 semi pair - plots 01, 02 | B5: 2 | C5: 389 | D5: 4 | E5: 1
A6: Block B02 - HT01 terrace of 3 - plots 03, 04, 05 | B6: 3 | C6: 508 | D6: 5 | E6: 1
A7: Block B03 - HT01 terrace of 3 - plots 06, 07, 08 | B7: 3 | C7: 521 | D7: 6 | E7: 1
A8: Block B04 - HT01 semi pair - plots 09, 10 | B8: 2 | C8: 380 | D8: 5 | E8: 2
A9: Block B05 - HT01 terrace of 3 - plots 11, 12, 13 | B9: 3 | C9: 526 | D9: 5 | E9: 3
A10: Block B06 - HT02 bungalow - plots 14 | B10: 1 | C10: 122 | D10: 4 | E10: 4
A11: Block B07 - HT02 bungalow - plots 15 | B11: 1 | C11: 129 | D11: 3 | E11: 5
A12: Block B08 - HT01 terrace of 3 - plots 16, 17, 18 | B12: 3 | C12: 518 | D12: 6 | E12: 5
A14: LEGEND
C15: ICF walls — FB + L1 lifts installed together (erection, snag & pour)
C16: ICF walls — each lift above the first, once the floor below it is in
C17: Concrete pour — 1 day per lift, ICF crew attends, pump on site
C18: Curing — pours held to Fridays where possible so the 2 curing days fall on the weekend; a mid-week pour cures 2 working days
C19: Floor structure — one per intermediate floor (FF, SF …), between wall lifts
C20: Roof structure (all-timber, trusses + rafters)
A22: RESOURCING
A23: • 1 ICF crews of 8 trained installers (each crew = 2 four-man gang-equivalents) erect the wall lifts, moving to the next ready block while a floor is fitted; 1 joinery crew of 3 fits every intermediate floor and roof (Joinery at 1 day per plot for each floor and 1 day per plot for each roof (Tom 19.10.26).). Programme is resource-levelled day by day (white = block waiting for a crew).
A24: • Total ICF site programme: 10 working weeks (ICF erection, floors and roofs). Section A Preliminaries are quantified against this 10-week programme.
A25: • EXTERNAL RENDER / FINISH IS EXCLUDED from this BOQ and this programme. Where a render system is later specified, allow a separate workstream — per BBA guidance, render cannot begin until the concrete core has cured for a minimum of 28 days after the final pour.
A26: • Concrete pump booked on the pour days for each group (see Section C).
A27: • Lead time for BuildEase Pre-Cut Service: 5–6 weeks from order placement; procurement runs in parallel with mobilisation.
A28: • Programme estimates are provided in good faith and must be verified by the project / site management team.

Sheet Summary
A1: SUMMARY OF TENDER PRICING
A3: Section totals are carried forward from each Bill section. Pre-priced columns show values from the associated Tremco CPG quotation; contractor-priced columns populate automatically when rates are entered in the section sheets. This BOQ excludes external render.
A5: Section | B5: Description | C5: Pre-priced (£) | D5: Contractor-priced (£) | E5: Section Total (£)
A6: A | B6: Preliminaries | D6: ='A_Preliminaries'!F1000 | E6: =IF(ISNUMBER(C6),C6,0)+IF(ISNUMBER(D6),D6,0)
A7: B | B7: ICF Kit Supply | C7: 196202.12 | E7: =IF(ISNUMBER(C7),C7,0)+IF(ISNUMBER(D7),D7,0)
A8: C | B8: Concrete Supply, Pump & Placement | D8: ='C_Concrete'!F1000 | E8: =IF(ISNUMBER(C8),C8,0)+IF(ISNUMBER(D8),D8,0)
A9: D | B9: Labour — ICF, Floors & Roofs | D9: ='D_Labour'!F1000 | E9: =IF(ISNUMBER(C9),C9,0)+IF(ISNUMBER(D9),D9,0)
B11: NET TOTAL (excluding VAT) | C11: =SUM(C6:C9) | D11: =SUM(D6:D9) | E11: =SUM(E6:E9)
B12: VAT @ 20% | E12: =E11*0.20
B13: GRAND TOTAL (inclusive of VAT) | E13: =E11+E12
A17: SIGNATURES
A19: Priced by
A20: Tendered by
A21: Approved by

Sheet A_Preliminaries
A1: A · PRELIMINARIES
A2: Items priced per working week against the site programme total of 10 weeks (see Programme sheet). Quantities are pre-populated; the contractor inserts the weekly rate.
A4: Ref | B4: Description | C4: Unit | D4: Qty | E4: Rate (£) | F4: Total (£)
A5: A.1 | B5: Site set-up, fencing, signage, induction & welfare establishment | C5: item | D5: 1 | F5: =IF(AND(ISNUMBER(D5),ISNUMBER(E5)),D5*E5,0)
A6: A.2 | B6: Welfare facilities — canteen, drying, toilets (hire) | C6: wk | D6: 10 | F6: =IF(AND(ISNUMBER(D6),ISNUMBER(E6)),D6*E6,0)
A7: A.3 | B7: Contract management & site supervision | C7: wk | D7: 10 | F7: =IF(AND(ISNUMBER(D7),ISNUMBER(E7)),D7*E7,0)
A8: A.4 | B8: Health & Safety, RAMS, CDM consultancy | C8: wk | D8: 10 | F8: =IF(AND(ISNUMBER(D8),ISNUMBER(E8)),D8*E8,0)
A9: A.5 | B9: Public liability and contract works insurance | C9: item | D9: 1 | F9: =IF(AND(ISNUMBER(D9),ISNUMBER(E9)),D9*E9,0)
A10: A.6 | B10: Scaffolding — independent access for ICF erection | C10: wk | D10: 10 | F10: =IF(AND(ISNUMBER(D10),ISNUMBER(E10)),D10*E10,0)
A11: A.7 | B11: Plant hire — telehandler / forklift for offload & ICF moves | C11: wk | D11: 10 | F11: =IF(AND(ISNUMBER(D11),ISNUMBER(E11)),D11*E11,0)
A12: A.8 | B12: Plant hire — small tools, generators, power & lighting | C12: wk | D12: 10 | F12: =IF(AND(ISNUMBER(D12),ISNUMBER(E12)),D12*E12,0)
A13: A.9 | B13: Hoarding / site enclosure / security | C13: wk | D13: 10 | F13: =IF(AND(ISNUMBER(D13),ISNUMBER(E13)),D13*E13,0)
A14: A.10 | B14: Temporary services — water, power, lighting (hire) | C14: wk | D14: 10 | F14: =IF(AND(ISNUMBER(D14),ISNUMBER(E14)),D14*E14,0)
A15: A.11 | B15: Site clean, waste management & skip rotation | C15: wk | D15: 10 | F15: =IF(AND(ISNUMBER(D15),ISNUMBER(E15)),D15*E15,0)
A16: A.12 | B16: Setting out and surveying — engineer's level checks | C16: wk | D16: 10 | F16: =IF(AND(ISNUMBER(D16),ISNUMBER(E16)),D16*E16,0)
A17: A.13 | B17: Site take-down, hand-over & demobilisation | C17: item | D17: 1 | F17: =IF(AND(ISNUMBER(D17),ISNUMBER(E17)),D17*E17,0)
A18: A.14 | B18: Pre-completion sound test (Approved Document E) | C18: test | F18: =IF(AND(ISNUMBER(D18),ISNUMBER(E18)),D18*E18,0)
A19: A.15 | B19: Air-tightness test (Approved Document L) | C19: test | F19: =IF(AND(ISNUMBER(D19),ISNUMBER(E19)),D19*E19,0)
A20: A.16 | B20: Day works allowance | C20: sum | F20: =IF(AND(ISNUMBER(D20),ISNUMBER(E20)),D20*E20,0)
B22: A — PRELIMINARIES SUBTOTAL | F22: =SUM(F5:F20)
F1000: =F22

Sheet B_ICF_Supply
A1: B · ICF KIT SUPPLY
A2: ICF material supply values are pre-priced from the associated Tremco CPG quotation. Pre-cut service fees are taken from each BuildEase take-off.
A4: Ref | B4: Description | C4: Unit | D4: Qty | E4: Rate (£) | F4: Total (£)
A5: B.1 — ICF Block, Forms & Accessories
A6: B.1 | B6: ICF Materials — Block B01 - HT01 semi pair - plots 01, 02 (2 plot(s), 389 forms) | C6: group | D6: 1 | E6: 21961.23 | F6: =IF(AND(ISNUMBER(D6),ISNUMBER(E6)),D6*E6,0)
A7: B.1 | B7: ICF Materials — Block B02 - HT01 terrace of 3 - plots 03, 04, 05 (3 plot(s), 508 forms) | C7: group | D7: 1 | E7: 28974.06 | F7: =IF(AND(ISNUMBER(D7),ISNUMBER(E7)),D7*E7,0)
A8: B.1 | B8: ICF Materials — Block B03 - HT01 terrace of 3 - plots 06, 07, 08 (3 plot(s), 521 forms) | C8: group | D8: 1 | E8: 29603.35 | F8: =IF(AND(ISNUMBER(D8),ISNUMBER(E8)),D8*E8,0)
A9: B.1 | B9: ICF Materials — Block B04 - HT01 semi pair - plots 09, 10 (2 plot(s), 380 forms) | C9: group | D9: 1 | E9: 21476.07 | F9: =IF(AND(ISNUMBER(D9),ISNUMBER(E9)),D9*E9,0)
A10: B.1 | B10: ICF Materials — Block B05 - HT01 terrace of 3 - plots 11, 12, 13 (3 plot(s), 526 forms) | C10: group | D10: 1 | E10: 29949.87 | F10: =IF(AND(ISNUMBER(D10),ISNUMBER(E10)),D10*E10,0)
A11: B.1 | B11: ICF Materials — Block B06 - HT02 bungalow - plots 14 (1 plot(s), 122 forms) | C11: group | D11: 1 | E11: 6975.24 | F11: =IF(AND(ISNUMBER(D11),ISNUMBER(E11)),D11*E11,0)
A12: B.1 | B12: ICF Materials — Block B07 - HT02 bungalow - plots 15 (1 plot(s), 129 forms) | C12: group | D12: 1 | E12: 7309.7 | F12: =IF(AND(ISNUMBER(D12),ISNUMBER(E12)),D12*E12,0)
A13: B.1 | B13: ICF Materials — Block B08 - HT01 terrace of 3 - plots 16, 17, 18 (3 plot(s), 518 forms) | C13: group | D13: 1 | E13: 29495.39 | F13: =IF(AND(ISNUMBER(D13),ISNUMBER(E13)),D13*E13,0)
A15: B.2 — BuildEase Pre-Cut Service Fee
A16: B.2 | B16: Pre-Cut Service — Block B01 - HT01 semi pair - plots 01, 02 | C16: group | D16: 1 | E16: 1689.77 | F16: =IF(AND(ISNUMBER(D16),ISNUMBER(E16)),D16*E16,0)
A17: B.2 | B17: Pre-Cut Service — Block B02 - HT01 terrace of 3 - plots 03, 04, 05 | C17: group | D17: 1 | E17: 2017.35 | F17: =IF(AND(ISNUMBER(D17),ISNUMBER(E17)),D17*E17,0)
A18: B.2 | B18: Pre-Cut Service — Block B03 - HT01 terrace of 3 - plots 06, 07, 08 | C18: group | D18: 1 | E18: 1322.49 | F18: =IF(AND(ISNUMBER(D18),ISNUMBER(E18)),D18*E18,0)
A19: B.2 | B19: Pre-Cut Service — Block B04 - HT01 semi pair - plots 09, 10 | C19: group | D19: 1 | E19: 1029.5 | F19: =IF(AND(ISNUMBER(D19),ISNUMBER(E19)),D19*E19,0)
A20: B.2 | B20: Pre-Cut Service — Block B05 - HT01 terrace of 3 - plots 11, 12, 13 | C20: group | D20: 1 | E20: 1331.98 | F20: =IF(AND(ISNUMBER(D20),ISNUMBER(E20)),D20*E20,0)
A21: B.2 | B21: Pre-Cut Service — Block B06 - HT02 bungalow - plots 14 | C21: group | D21: 1 | E21: 1116.94 | F21: =IF(AND(ISNUMBER(D21),ISNUMBER(E21)),D21*E21,0)
A22: B.2 | B22: Pre-Cut Service — Block B07 - HT02 bungalow - plots 15 | C22: group | D22: 1 | E22: 657.56 | F22: =IF(AND(ISNUMBER(D22),ISNUMBER(E22)),D22*E22,0)
A23: B.2 | B23: Pre-Cut Service — Block B08 - HT01 terrace of 3 - plots 16, 17, 18 | C23: group | D23: 1 | E23: 1290.28 | F23: =IF(AND(ISNUMBER(D23),ISNUMBER(E23)),D23*E23,0)
A25: B.3 — Haulage
A26: B.3 | B26: Haulage to site — project-wide estimate (TBC on delivery schedule) | C26: item | D26: 1 | E26: 9041.34 | F26: =IF(AND(ISNUMBER(D26),ISNUMBER(E26)),D26*E26,0)
A28: B.4 — Alignment System
A29: B.4 | B29: Alignment System Rental — Block B01 - HT01 semi pair - plots 01, 02 (37 systems) | C29: group | D29: 1 | E29: 96 | F29: =IF(AND(ISNUMBER(D29),ISNUMBER(E29)),D29*E29,0)
A30: B.4 | B30: Alignment System Rental — Block B02 - HT01 terrace of 3 - plots 03, 04, 05 (50 systems) | C30: group | D30: 1 | E30: 144 | F30: =IF(AND(ISNUMBER(D30),ISNUMBER(E30)),D30*E30,0)
A31: B.4 | B31: Alignment System Rental — Block B03 - HT01 terrace of 3 - plots 06, 07, 08 (50 systems) | C31: group | D31: 1 | E31: 144 | F31: =IF(AND(ISNUMBER(D31),ISNUMBER(E31)),D31*E31,0)
A32: B.4 | B32: Alignment System Rental — Block B04 - HT01 semi pair - plots 09, 10 (37 systems) | C32: group | D32: 1 | E32: 96 | F32: =IF(AND(ISNUMBER(D32),ISNUMBER(E32)),D32*E32,0)
A33: B.4 | B33: Alignment System Rental — Block B05 - HT01 terrace of 3 - plots 11, 12, 13 (50 systems) | C33: group | D33: 1 | E33: 144 | F33: =IF(AND(ISNUMBER(D33),ISNUMBER(E33)),D33*E33,0)
A34: B.4 | B34: Alignment System Rental — Block B06 - HT02 bungalow - plots 14 (28 systems) | C34: group | D34: 1 | E34: 96 | F34: =IF(AND(ISNUMBER(D34),ISNUMBER(E34)),D34*E34,0)
A35: B.4 | B35: Alignment System Rental — Block B07 - HT02 bungalow - plots 15 (28 systems) | C35: group | D35: 1 | E35: 96 | F35: =IF(AND(ISNUMBER(D35),ISNUMBER(E35)),D35*E35,0)
A36: B.4 | B36: Alignment System Rental — Block B08 - HT01 terrace of 3 - plots 16, 17, 18 (50 systems) | C36: group | D36: 1 | E36: 144 | F36: =IF(AND(ISNUMBER(D36),ISNUMBER(E36)),D36*E36,0)
B38: B — ICF KIT SUPPLY SUBTOTAL | F38: =SUM(F5:F36)
F1000: =F38

Sheet C_Concrete
A1: C · CONCRETE SUPPLY, PUMP & PLACEMENT
A2: Volumes are geometric void calculations (block length × course height × core thickness). Allow ~3% for plastic web displacement and ~5% wastage when ordering. Rates to be inserted by the contractor.
A4: Ref | B4: Description | C4: Unit | D4: Qty | E4: Rate (£) | F4: Total (£)
A5: C.1 — Ready-Mix Concrete Supply (C28/35 typical to BS 8500)
A6: C.1 | B6: Ready-mix concrete — Block B01 - HT01 semi pair - plots 01, 02 (2 plot(s), geometric void) | C6: m³ | D6: 62.77 | F6: =IF(AND(ISNUMBER(D6),ISNUMBER(E6)),D6*E6,0)
A7: C.1 | B7: Ready-mix concrete — Block B02 - HT01 terrace of 3 - plots 03, 04, 05 (3 plot(s), geometric void) | C7: m³ | D7: 83.05 | F7: =IF(AND(ISNUMBER(D7),ISNUMBER(E7)),D7*E7,0)
A8: C.1 | B8: Ready-mix concrete — Block B03 - HT01 terrace of 3 - plots 06, 07, 08 (3 plot(s), geometric void) | C8: m³ | D8: 85.14 | F8: =IF(AND(ISNUMBER(D8),ISNUMBER(E8)),D8*E8,0)
A9: C.1 | B9: Ready-mix concrete — Block B04 - HT01 semi pair - plots 09, 10 (2 plot(s), geometric void) | C9: m³ | D9: 61.24 | F9: =IF(AND(ISNUMBER(D9),ISNUMBER(E9)),D9*E9,0)
A10: C.1 | B10: Ready-mix concrete — Block B05 - HT01 terrace of 3 - plots 11, 12, 13 (3 plot(s), geometric void) | C10: m³ | D10: 85.99 | F10: =IF(AND(ISNUMBER(D10),ISNUMBER(E10)),D10*E10,0)
A11: C.1 | B11: Ready-mix concrete — Block B06 - HT02 bungalow - plots 14 (1 plot(s), geometric void) | C11: m³ | D11: 18.92 | F11: =IF(AND(ISNUMBER(D11),ISNUMBER(E11)),D11*E11,0)
A12: C.1 | B12: Ready-mix concrete — Block B07 - HT02 bungalow - plots 15 (1 plot(s), geometric void) | C12: m³ | D12: 20 | F12: =IF(AND(ISNUMBER(D12),ISNUMBER(E12)),D12*E12,0)
A13: C.1 | B13: Ready-mix concrete — Block B08 - HT01 terrace of 3 - plots 16, 17, 18 (3 plot(s), geometric void) | C13: m³ | D13: 84.63 | F13: =IF(AND(ISNUMBER(D13),ISNUMBER(E13)),D13*E13,0)
A15: C.2 — Concrete Pump Hire
A16: C.2 | B16: Boom pump hire — Block B01 - HT01 semi pair - plots 01, 02 | C16: day | D16: 2 | F16: =IF(AND(ISNUMBER(D16),ISNUMBER(E16)),D16*E16,0)
A17: C.2 | B17: Boom pump hire — Block B02 - HT01 terrace of 3 - plots 03, 04, 05 | C17: day | D17: 2 | F17: =IF(AND(ISNUMBER(D17),ISNUMBER(E17)),D17*E17,0)
A18: C.2 | B18: Boom pump hire — Block B03 - HT01 terrace of 3 - plots 06, 07, 08 | C18: day | D18: 2 | F18: =IF(AND(ISNUMBER(D18),ISNUMBER(E18)),D18*E18,0)
A19: C.2 | B19: Boom pump hire — Block B04 - HT01 semi pair - plots 09, 10 | C19: day | D19: 2 | F19: =IF(AND(ISNUMBER(D19),ISNUMBER(E19)),D19*E19,0)
A20: C.2 | B20: Boom pump hire — Block B05 - HT01 terrace of 3 - plots 11, 12, 13 | C20: day | D20: 2 | F20: =IF(AND(ISNUMBER(D20),ISNUMBER(E20)),D20*E20,0)
A21: C.2 | B21: Boom pump hire — Block B06 - HT02 bungalow - plots 14 | C21: day | D21: 2 | F21: =IF(AND(ISNUMBER(D21),ISNUMBER(E21)),D21*E21,0)
A22: C.2 | B22: Boom pump hire — Block B07 - HT02 bungalow - plots 15 | C22: day | D22: 2 | F22: =IF(AND(ISNUMBER(D22),ISNUMBER(E22)),D22*E22,0)
A23: C.2 | B23: Boom pump hire — Block B08 - HT01 terrace of 3 - plots 16, 17, 18 | C23: day | D23: 2 | F23: =IF(AND(ISNUMBER(D23),ISNUMBER(E23)),D23*E23,0)
A24: C.2 | B24: Pump mobilisation / demobilisation | C24: item | D24: 1 | F24: =IF(AND(ISNUMBER(D24),ISNUMBER(E24)),D24*E24,0)
A26: C.3 — Concrete Vibration & Placement Plant
A27: C.3 | B27: Internal poker vibrator hire — site duration | C27: wk | D27: 10 | F27: =IF(AND(ISNUMBER(D27),ISNUMBER(E27)),D27*E27,0)
A28: C.3 | B28: Concrete banksman / poker operator | C28: day | F28: =IF(AND(ISNUMBER(D28),ISNUMBER(E28)),D28*E28,0)
B30: C — CONCRETE SUBTOTAL | F30: =SUM(F5:F28)
F1000: =F30

Sheet D_Labour
A1: D · LABOUR — ICF INSTALL, FLOORS & ROOFS
A2: ICF install days scaled proportionately against the Maycroft reference (52.65 forms per gang-day). Rates below are per 4-man gang per day. Floor and roof allowances are taken per group from the project configuration.
A4: Ref | B4: Description | C4: Unit | D4: Qty | E4: Rate (£) | F4: Total (£)
A5: D.1 — ICF Install Gang
A6: D.1 | B6: ICF install — Block B01 - HT01 semi pair - plots 01, 02 (389 forms ÷ 52.65 forms/day = 7.4 gang-days) | C6: gang-day | D6: 7.4 | F6: =IF(AND(ISNUMBER(D6),ISNUMBER(E6)),D6*E6,0)
A7: D.1 | B7: ICF install — Block B02 - HT01 terrace of 3 - plots 03, 04, 05 (508 forms ÷ 52.65 forms/day = 9.6 gang-days) | C7: gang-day | D7: 9.6 | F7: =IF(AND(ISNUMBER(D7),ISNUMBER(E7)),D7*E7,0)
A8: D.1 | B8: ICF install — Block B03 - HT01 terrace of 3 - plots 06, 07, 08 (521 forms ÷ 52.65 forms/day = 9.9 gang-days) | C8: gang-day | D8: 9.9 | F8: =IF(AND(ISNUMBER(D8),ISNUMBER(E8)),D8*E8,0)
A9: D.1 | B9: ICF install — Block B04 - HT01 semi pair - plots 09, 10 (380 forms ÷ 52.65 forms/day = 7.2 gang-days) | C9: gang-day | D9: 7.2 | F9: =IF(AND(ISNUMBER(D9),ISNUMBER(E9)),D9*E9,0)
A10: D.1 | B10: ICF install — Block B05 - HT01 terrace of 3 - plots 11, 12, 13 (526 forms ÷ 52.65 forms/day = 10.0 gang-days) | C10: gang-day | D10: 10 | F10: =IF(AND(ISNUMBER(D10),ISNUMBER(E10)),D10*E10,0)
A11: D.1 | B11: ICF install — Block B06 - HT02 bungalow - plots 14 (122 forms ÷ 52.65 forms/day = 2.3 gang-days) | C11: gang-day | D11: 2.3 | F11: =IF(AND(ISNUMBER(D11),ISNUMBER(E11)),D11*E11,0)
A12: D.1 | B12: ICF install — Block B07 - HT02 bungalow - plots 15 (129 forms ÷ 52.65 forms/day = 2.5 gang-days) | C12: gang-day | D12: 2.5 | F12: =IF(AND(ISNUMBER(D12),ISNUMBER(E12)),D12*E12,0)
A13: D.1 | B13: ICF install — Block B08 - HT01 terrace of 3 - plots 16, 17, 18 (518 forms ÷ 52.65 forms/day = 9.8 gang-days) | C13: gang-day | D13: 9.8 | F13: =IF(AND(ISNUMBER(D13),ISNUMBER(E13)),D13*E13,0)
A14: D.1 | B14: Snag, pour & cure attendance (30% allowance, project total) | C14: gang-day | D14: 17.6 | F14: =IF(AND(ISNUMBER(D14),ISNUMBER(E14)),D14*E14,0)
A16: D.2 — Floor Structure Labour (metal-web joists, top-hung balloon frame)
A17: D.2 | B17: Floor structure — Block B01 - HT01 semi pair - plots 01, 02 (1 floor × 2 gang-days) | C17: gang-day | D17: 2 | F17: =IF(AND(ISNUMBER(D17),ISNUMBER(E17)),D17*E17,0)
A18: D.2 | B18: Floor structure — Block B02 - HT01 terrace of 3 - plots 03, 04, 05 (1 floor × 3 gang-days) | C18: gang-day | D18: 3 | F18: =IF(AND(ISNUMBER(D18),ISNUMBER(E18)),D18*E18,0)
A19: D.2 | B19: Floor structure — Block B03 - HT01 terrace of 3 - plots 06, 07, 08 (1 floor × 3 gang-days) | C19: gang-day | D19: 3 | F19: =IF(AND(ISNUMBER(D19),ISNUMBER(E19)),D19*E19,0)
A20: D.2 | B20: Floor structure — Block B04 - HT01 semi pair - plots 09, 10 (1 floor × 2 gang-days) | C20: gang-day | D20: 2 | F20: =IF(AND(ISNUMBER(D20),ISNUMBER(E20)),D20*E20,0)
A21: D.2 | B21: Floor structure — Block B05 - HT01 terrace of 3 - plots 11, 12, 13 (1 floor × 3 gang-days) | C21: gang-day | D21: 3 | F21: =IF(AND(ISNUMBER(D21),ISNUMBER(E21)),D21*E21,0)
A22: D.2 | B22: Floor structure — Block B08 - HT01 terrace of 3 - plots 16, 17, 18 (1 floor × 3 gang-days) | C22: gang-day | D22: 3 | F22: =IF(AND(ISNUMBER(D22),ISNUMBER(E22)),D22*E22,0)
A24: D.3 — Roof Structure Labour (trusses + rafters, all-timber)
A25: D.3 | B25: Roof structure — Block B01 - HT01 semi pair - plots 01, 02 | C25: gang-day | D25: 2 | F25: =IF(AND(ISNUMBER(D25),ISNUMBER(E25)),D25*E25,0)
A26: D.3 | B26: Roof structure — Block B02 - HT01 terrace of 3 - plots 03, 04, 05 | C26: gang-day | D26: 3 | F26: =IF(AND(ISNUMBER(D26),ISNUMBER(E26)),D26*E26,0)
A27: D.3 | B27: Roof structure — Block B03 - HT01 terrace of 3 - plots 06, 07, 08 | C27: gang-day | D27: 3 | F27: =IF(AND(ISNUMBER(D27),ISNUMBER(E27)),D27*E27,0)
A28: D.3 | B28: Roof structure — Block B04 - HT01 semi pair - plots 09, 10 | C28: gang-day | D28: 2 | F28: =IF(AND(ISNUMBER(D28),ISNUMBER(E28)),D28*E28,0)
A29: D.3 | B29: Roof structure — Block B05 - HT01 terrace of 3 - plots 11, 12, 13 | C29: gang-day | D29: 3 | F29: =IF(AND(ISNUMBER(D29),ISNUMBER(E29)),D29*E29,0)
A30: D.3 | B30: Roof structure — Block B06 - HT02 bungalow - plots 14 | C30: gang-day | D30: 1 | F30: =IF(AND(ISNUMBER(D30),ISNUMBER(E30)),D30*E30,0)
A31: D.3 | B31: Roof structure — Block B07 - HT02 bungalow - plots 15 | C31: gang-day | D31: 1 | F31: =IF(AND(ISNUMBER(D31),ISNUMBER(E31)),D31*E31,0)
A32: D.3 | B32: Roof structure — Block B08 - HT01 terrace of 3 - plots 16, 17, 18 | C32: gang-day | D32: 3 | F32: =IF(AND(ISNUMBER(D32),ISNUMBER(E32)),D32*E32,0)
B34: D — LABOUR SUBTOTAL | F34: =SUM(F5:F32)
F1000: =F34

Sheet F_Reference
A1: F · REFERENCE DATA (informative only)
A2: Per-group quantities calculated from the BuildEase take-off models. Values feed into Sections C and D. Render is excluded from this BOQ.
A4: Group | B4: Plots | C4: Forms | D4: Concrete (m³) | E4: ICF install days | F4: Floor + Roof days | G4: Pre-cut (£)
A5: Block B01 - HT01 semi pair - plots 01, 02 | B5: 2 | C5: 389 | D5: 62.77 | E5: 7.4 | F5: 4 | G5: 1689.77
A6: Block B02 - HT01 terrace of 3 - plots 03, 04, 05 | B6: 3 | C6: 508 | D6: 83.05 | E6: 9.6 | F6: 6 | G6: 2017.35
A7: Block B03 - HT01 terrace of 3 - plots 06, 07, 08 | B7: 3 | C7: 521 | D7: 85.14 | E7: 9.9 | F7: 6 | G7: 1322.49
A8: Block B04 - HT01 semi pair - plots 09, 10 | B8: 2 | C8: 380 | D8: 61.24 | E8: 7.2 | F8: 4 | G8: 1029.5
A9: Block B05 - HT01 terrace of 3 - plots 11, 12, 13 | B9: 3 | C9: 526 | D9: 85.99 | E9: 10 | F9: 6 | G9: 1331.98
A10: Block B06 - HT02 bungalow - plots 14 | B10: 1 | C10: 122 | D10: 18.92 | E10: 2.3 | F10: 1 | G10: 1116.94
A11: Block B07 - HT02 bungalow - plots 15 | B11: 1 | C11: 129 | D11: 20 | E11: 2.5 | F11: 1 | G11: 657.56
A12: Block B08 - HT01 terrace of 3 - plots 16, 17, 18 | B12: 3 | C12: 518 | D12: 84.63 | E12: 9.8 | F12: 6 | G12: 1290.28
A13: SITE | B13: 18 | C13: 3093 | D13: 501.75 | E13: 58.7 | F13: 34 | G13: 10455.87
A16: PER-LIFT FORM BREAKDOWN
A17: Group | B17: Lift | C17: 4" Std | D17: 6" XR35 str | E17: 6" XR35 cnr | F17: 10" Std | G17: Lift total
A18: Block B01 - HT01 semi pair - plots 01, 02 | B18: FB | C18: 0 | D18: 57 | E18: 11 | F18: 0 | G18: 68
A19: Block B01 - HT01 semi pair - plots 01, 02 | B19: L1 | C19: 0 | D19: 109 | E19: 24 | F19: 0 | G19: 133
A20: Block B01 - HT01 semi pair - plots 01, 02 | B20: L2 | C20: 0 | D20: 164 | E20: 24 | F20: 0 | G20: 188
A21: Block B02 - HT01 terrace of 3 - plots 03, 04, 05 | B21: FB | C21: 0 | D21: 70 | E21: 10 | F21: 0 | G21: 80
A22: Block B02 - HT01 terrace of 3 - plots 03, 04, 05 | B22: L1 | C22: 0 | D22: 154 | E22: 24 | F22: 0 | G22: 178
A23: Block B02 - HT01 terrace of 3 - plots 03, 04, 05 | B23: L2 | C23: 0 | D23: 226 | E23: 24 | F23: 0 | G23: 250
A24: Block B03 - HT01 terrace of 3 - plots 06, 07, 08 | B24: FB | C24: 0 | D24: 81 | E24: 12 | F24: 0 | G24: 93
A25: Block B03 - HT01 terrace of 3 - plots 06, 07, 08 | B25: L1 | C25: 0 | D25: 154 | E25: 24 | F25: 0 | G25: 178
A26: Block B03 - HT01 terrace of 3 - plots 06, 07, 08 | B26: L2 | C26: 0 | D26: 226 | E26: 24 | F26: 0 | G26: 250
A27: Block B04 - HT01 semi pair - plots 09, 10 | B27: FB | C27: 0 | D27: 48 | E27: 11 | F27: 0 | G27: 59
A28: Block B04 - HT01 semi pair - plots 09, 10 | B28: L1 | C28: 0 | D28: 109 | E28: 24 | F28: 0 | G28: 133
A29: Block B04 - HT01 semi pair - plots 09, 10 | B29: L2 | C29: 0 | D29: 164 | E29: 24 | F29: 0 | G29: 188
... A39: Block B08 - HT01 terrace of 3 - plots 16, 17, 18 | B39: L2 | C39: 0 | D39: 226 | E39: 24 | F39: 0 | G39: 250
A42: GEOMETRIC CONSTANTS & CALCULATION BASIS
A43: Block length | C43: 2.438 m | E43: 96 inches
A44: Course height | C44: 0.4574 m | E44: 18 inches
A45: 4" Std straight volume | C45: 0.1133 m³ | E45: =length × course × core
A46: 6" XR35 straight volume | C46: 0.1699 m³ | E46: =length × course × core
A47: 10" Std straight volume | C47: 0.2832 m³ | E47: =length × course × core
A48: 4" Std corner volume | C48: 0.0511 m³ | E48: L-void; long 31.625" / short 15.625"
A49: 6" XR35 corner volume | C49: 0.1133 m³ | E49: L-void; long 43" / short 27"
A50: Maycroft install rate | C50: 52.65 forms/day | E50: Reference: 1053 forms ÷ 20 days

Sheet Finishes Cover
C1: Bill of Quantities Package - Finishes & Ancillary Trades
C2: ES26-080 | Land to Rear of 1-8 Wesley Terrace, Castleside | Wannop Developments Ltd
A4: DISCLAIMER: This information is supplied in good faith for guidance and coordination only. It is not part of the Nudura ICF price and must be checked and verified by the appropriate professional (quantity surveyor, designer, engineer or supplier) before use. Only the Nudura ICF formwork and associated accessories are included in our price. Quantities are measured from the quotation models and the SK11A drawings (DRAFT); no allowance for waste is included unless stated. Quantities are per block for each block type; the Site total multiplies by the number of blocks. Rates and amounts are by others.
A6: Project | B6: Land to Rear of 1-8 Wesley Terrace, Castleside
A7: Site | B7: Land to Rear of 1-8 Wesley Terrace, Castleside, County Durham DH8 9QB
A8: Client | B8: Wannop Developments Ltd
A9: Architect | B9: Code L6 Architecture Ltd (24-014, drawings SK11A / 10G, DRAFT)
A10: Quotation ref | B10: ES26-080
A11: Document | B11: Bill of Quantities Package - Finishes & Ancillary Trades
A12: Issue | B12: 01 (19/10/2026)
A13: Scope | B13: 18 dwellings in 8 blocks: HT01 3-bed 2-storey houses as 2 semi pairs (B01, B04) and 4 terraces of 3 (B02, B03, B05 brick; B08 stone, plots 16-18); HT02 2-bed detached bungalows (B06, B07, plots 14-15)
A14: Prepared by | B14: BuildEase (Tremco CPG UK) - BuildEase Design Suite quotation models
A15: Status | B15: FOR INFORMATION, COORDINATION AND PRICING BY OTHERS - rates blank; NOT part of the Nudura ICF price
A17: PACKAGE OVERVIEW - pricing by others (all amounts formula-linked to each bill's Package Summary)
A18: Bill | B18: Package | C18: Code / NRM2 | D18: Supply £ | E18: Install £ | F18: Total £
A19: Bill 1 | B19: External Wall Finishes - Brick & Stone Slips | C19: CLD NRM2 21 | D19: ='Bill 1 External Finishes'!K44 | E19: ='Bill 1 External Finishes'!L44 | F19: ='Bill 1 External Finishes'!M44
A20: Bill 2 | B20: Internal Linings - Plasterboard, Tape, Beads & Skim | C20: DRY NRM2 28 | D20: ='Bill 2 Internal Linings'!K40 | E20: ='Bill 2 Internal Linings'!L40 | F20: ='Bill 2 Internal Linings'!M40
A21: Bill 3 | B21: Internal Doors & Ironmongery | C21: JOI NRM2 24 | D21: ='Bill 3 Doors'!K31 | E21: ='Bill 3 Doors'!L31 | F21: ='Bill 3 Doors'!M31
A22: Bill 4 | B22: Joinery - Skirtings, Architraves, Window Boards & Loft Hatches | C22: JOI NRM2 22 | D22: ='Bill 4 Joinery'!K44 | E22: ='Bill 4 Joinery'!L44 | F22: ='Bill 4 Joinery'!M44
A23: Bill 5 | B23: Timber Stud Partitions - Framing, Openings, Pattresses & Fixings | C23: JOI NRM2 16 | D23: ='Bill 5 Partitions'!K47 | E23: ='Bill 5 Partitions'!L47 | F23: ='Bill 5 Partitions'!M47
A24: GRAND TOTAL - finishes / ancillary trades, net (excl. VAT) | D24: =SUM(D19:D23) | E24: =SUM(E19:E23) | F24: =SUM(F19:F23)
A26: Optional additions (enter %; blank = 0) | C26: % | F26: Amount £
A27: Preliminaries | B27: on the finishes net grand total | F27: =(F24)*N(C27)
A28: Overheads & profit | B28: on net total + preliminaries | F28: =(F24+F27)*N(C28)
A29: Contingency | B29: on net total + preliminaries + OH&P | F29: =(F24+F27+F28)*N(C29)
A30: GRAND TOTAL finishes incl. preliminaries, OH&P and contingency (excl. VAT) | F30: =F24+F27+F28+F29
A32: ICF PACKAGE HOOK - BuildEase BOQ Builder (ICF kit, concrete, labour, preliminaries, programme)
A33: Nudura ICF package (BuildEase BOQ Builder) | F33: ='Summary'!$E$11
A34: COMBINED TOTAL - finishes package (incl. additions) + ICF package, excl. VAT | F34: =F30+N(F33)
A35: Pale-yellow cells are the only inputs (rates on each bill sheet, percentages and the ICF hook here). Everything else is a locked formula (protection has no password). Schedules A to D are reference only and are not priced. Named cells: FINISHES_NET_TOTAL, FINISHES_GRAND_TOTAL, ICF_PACKAGE_TOTAL, COMBINED_TOTAL.
A37: IMPORTANT - This information is supplied in good faith for guidance and coordination only. It is not part of the Nudura ICF price and must be checked and verified by the appropriate professional (quantity surveyor, designer, engineer or supplier) before use. Only the Nudura ICF formwork and associated accessories are included in our price. Quantities are measured from the quotation models and the SK11A drawings (DRAFT); no allowance for waste is included unless stated. Quantities are per block for each block type; the Site total multiplies by the number of blocks. Rates and amounts are by others.
A39: KEY QUANTITIES (site totals, 8 blocks / 18 plots, net; linked to the bills)
A40: Brick slips, walls (net, excl. reveals) | D40: ='Bill 1 External Finishes'!H10+'Bill 1 External Finishes'!H11+'Bill 1 External Finishes'!H12+'Bill 1 External Finishes'!H13 | E40: m2
A41: Stone slips, walls (net, excl. reveals) | D41: ='Bill 1 External Finishes'!H22+'Bill 1 External Finishes'!H23+'Bill 1 External Finishes'!H24 | E41: m2
A42: Plasterboard, walls, reveals and bands (net) | D42: ='Bill 2 Internal Linings'!H10+'Bill 2 Internal Linings'!H11+'Bill 2 Internal Linings'!H12+'Bill 2 Internal Linings'!H13+'Bill 2 Internal Linings'!H14+'Bill 2 Internal Linings'!H15+'Bill 2 Internal Linings'!H16+'Bill 2 Internal Linings'!H17+'Bill 2 Internal Linings'!H18 | E42: m2
A43: Plasterboard, ceilings and stair soffits (net) | D43: ='Bill 2 Internal Linings'!H21+'Bill 2 Internal Linings'!H22+'Bill 2 Internal Linings'!H23+'Bill 2 Internal Linings'!H24 | E43: m2
A44: Skim coat | D44: ='Bill 2 Internal Linings'!H31 | E44: m2
A45: Internal doorsets | D45: ='Bill 3 Doors'!H10+'Bill 3 Doors'!H11+'Bill 3 Doors'!H12+'Bill 3 Doors'!H13 | E45: nr
A46: Skirting | D46: ='Bill 4 Joinery'!H24 | E46: m
A47: Architrave | D47: ='Bill 4 Joinery'!H27+'Bill 4 Joinery'!H28 | E47: m
A48: Window boards | D48: ='Bill 4 Joinery'!H31+'Bill 4 Joinery'!H32+'Bill 4 Joinery'!H33 | E48: nr
A49: Timber stud partitions (gross area) | D49: ='Bill 5 Partitions'!H10+'Bill 5 Partitions'!H11+'Bill 5 Partitions'!H12+'Bill 5 Partitions'!H13+'Bill 5 Partitions'!H14+'Bill 5 Partitions'!H15 | E49: m2
A50: Partition timber 38 x 89 C16 (estimate) | D50: ='Bill 5 Partitions'!H18+'Bill 5 Partitions'!H19+'Bill 5 Partitions'!H20 | E50: m
A51: Door openings formed in partitions | D51: ='Bill 5 Partitions'!H24+'Bill 5 Partitions'!H25+'Bill 5 Partitions'!H26 | E51: nr
A53: Document control
A54: Issue | B54: Description | C54: Date | D54: By / Status
A55: 01 | B55: First issue: finishes / ancillary-trades BOQ package from the quotation models (port of the ES26-081 package). Live pricing workbook: supply and install rates, package summaries and cover overview by formula; rates blank for pricing by others; ICF_PACKAGE_TOTAL hook for merging with the BOQ Builder ICF + programme workbook | C55: 19/10/2026 | D55: BuildEase - T. Smith / For information / pricing by others
A57: Contents
A58: Finishes Cover (this sheet) - overview
A59: General Notes
A60: Summary of Bills (section breakdown)
A61: Finishes Bill 1 External Finish
A62: Finishes Bill 2 Internal Lining
A63: Finishes Bill 3 Doors
A64: Finishes Bill 4 Joinery
A65: Finishes Bill 5 Partitions
A66: Schedule A Floor Areas (not priced)
A67: Schedule B Openings (not priced)
A68: Schedule C Per Plot (not priced)
A69: Schedule D Sloping Plots (not priced)

Sheet General Notes
B1: General Notes, Measurement Basis, Assumptions & Exclusions
B2: ES26-080 | Land to Rear of 1-8 Wesley Terrace, Castleside | Wannop Developments Ltd
A4: DISCLAIMER: This information is supplied in good faith for guidance and coordination only. It is not part of the Nudura ICF price and must be checked and verified by the appropriate professional (quantity surveyor, designer, engineer or supplier) before use. Only the Nudura ICF formwork and associated accessories are included in our price. Quantities are measured from the quotation models and the SK11A drawings (DRAFT); no allowance for waste is included unless stated. Quantities are per block for each block type; the Site total multiplies by the number of blocks. Rates and amounts are by others.
A6: 1 Purpose and status
A7: 1.1 | B7: This package presents the finishes and ancillary-trade quantities measured by BuildEase alongside the Nudura ICF quotation for Land to Rear of 1-8 Wesley Terrace, Castleside (ref ES26-080). It is set out in the form of a Bill of Quantities so that the client, their quantity surveyor and trade contractors can price and coordinate the works.
A8: 1.2 | B8: Status: FOR INFORMATION, COORDINATION AND PRICING BY OTHERS. Supply and install rates are left blank deliberately - BuildEase / Tremco CPG are not pricing these trades. The Excel workbook is a live pricing document: enter rates and every amount, section subtotal, package total and the cover overview update by formula.
A9: 1.3 | B9: The ICF kit, concrete core, pumping and ICF / floor / roof labour and the build programme are in the separate BuildEase BOQ Builder workbook. The cover of this workbook carries a named hook (ICF_PACKAGE_TOTAL) so the two can be combined into one workbook and one grand total.
A10: 1.4 | B10: This information is supplied in good faith for guidance and coordination only. It is not part of the Nudura ICF price and must be checked and verified by the appropriate professional (quantity surveyor, designer, engineer or supplier) before use. Only the Nudura ICF formwork and associated accessories are included in our price.
A11: 1.5 | B11: Quantities are measured from the quotation models and the SK11A drawings (DRAFT); no allowance for waste is included unless stated. Quantities are per block for each block type; the Site total multiplies by the number of blocks. Rates and amounts are by others.
A13: 2 Basis of measurement
A14: 2.1 | B14: Measured generally in accordance with the principles of NRM2 (RICS New Rules of Measurement, Detailed measurement for building works): work measured net as fixed in position, items grouped by work section, units m / m2 / nr / item. NRM2 is referenced for structure only; descriptions are BuildEase's own.
A15: 2.2 | B15: Quantities are NET. No allowance for waste, laps, cutting or breakage is included unless stated. Where useful an "Order guide" with a stated waste % is given in the Notes column; it is guidance only.
A16: 2.3 | B16: Quantity columns: one column PER BLOCK for each block type - T01_SEMI (B01, B04; plots 01-02, 09-10), T01_TER3 brick (B02, B03, B05; plots 03-08, 11-13), T01_TER3 stone (B08; plots 16-18) and T02_BUNG (B06, B07; plots 14, 15). The Site total = sum of (per-block quantity x number of blocks) and is a live formula. Mid-terrace units differ slightly from end units (party walls both sides); Schedule C lists the key quantities plot by plot.
A17: 2.4 | B17: Sources: Code L6 drawings 24-014-SK11A (house types, plans and elevations, 1:100 @ A1, DRAFT) and 24-014-10G (site plan, DRAFT); the BuildEase quotation models per block type (03_Models WD_T01_SEMI / WD_T01_TER3 / WD_T02_BUNG) through their specs (04_Logs/specs WD_spec*.json, WD_partitions.json) and build reports (04_Logs/build: floor / stair, TLSTF partition, pattress and noggin reports). Measured offline by 05_Scripts/wd_xi_takeoff.py; presented by wd_boq.py.
A19: 3 Assumptions
A20: 3.1 | B20: Walls: external ICF 6in XR35 (355.6 mm) set out on the drawn outer face; party walls 6in Std (285.75 mm). External finish: brick to units 01-15 (incl. bungalows 14-15) and stone to units 16-18 (SK11A elevations), taken as slip systems on the ICF - the ICF occupies the drawn wall thickness, so a full masonry outer leaf would need the set-out changed (confirm with the architect).
A21: 3.2 | B21: Windows / doors set 1/3 back from the outer ICF face (118.5 mm). External reveal = set-back + slip (brick 25 mm / stone 30 mm). Internal reveal = 195 mm (ICF less set-back less frame 70 plus lining 27.5).
A22: 3.3 | B22: Finish heights: from DPC (FFL - 150) to eaves 5,320 (HT01) / 2,320 (HT02); HT01 gables to the drawn brick apex 8,255. Lining heights: HT01 GF 2,425 (u/s joists), FF 2,700-5,370; HT02 2,336.
A23: 3.4 | B23: Plasterboard: 12.5 mm wallboard to ICF faces (MR in wet rooms); 15 mm sound / fire board to party walls; 15 mm each side of the 38 x 89 stud partitions; 12.5 mm ceilings, plus VCL under the trusses. Board types are proposals.
A24: 3.5 | B24: Doors: 900 / 800 / 700 mm gaps -> 826 / 726 / 626 x 2040 leaves; no fire doors in the houses or bungalows. Cupboard ironmongery counted per leaf; flush bolt per double door (none on this job).
A25: 3.6 | B25: Sloping site: per-block FFL = mean of the four existing corner ground levels + 150 (the stepped-footing rule used in the model). Items 1C are provisional.
A27: 4 Exclusions (not measured in this package)
A28: 4.1 | B28: Nudura ICF formwork and accessories (in the Nudura price - see section 6). Concrete core, pumping, ICF / floor / roof labour and preliminaries are in the BuildEase BOQ Builder ICF + programme workbook.
A29: 4.2 | B29: Supply of windows and external doorsets and cills (listed for coordination only), roof trusses, coverings, soffits, fascias and rainwater goods, FF floor joists and deck, staircases and balustrades, ground-bearing slab / screed / floor insulation.
A30: 4.3 | B30: Floor finishes, decorations, kitchens, sanitaryware, M&E services and builder's work, external works and drainage (other than as 1C).
A31: 4.4 | B31: Fire-stopping, cavity barriers, acoustic / thermal insulation to partitions, floors and lofts, sealants and mastics, except where expressly described.
A33: 5 Items to be confirmed
A34: 5.1 | B34: SK11A and 10G are marked DRAFT - quantities follow the draft drawings and the models built from them.
A35: 5.2 | B35: External finish build-ups (brick slip and stone slip systems over ICF) and whether a full masonry outer leaf is intended.
A36: 5.3 | B36: Final external levels: 1C.1 / 1C.2 are from the existing survey and the FFL rule; re-measure on the designed levels (falls up to 2.25 m within B03 / B05 / B08).
A37: 5.4 | B37: Partition timber (5B) is an estimate - the TLSTF construction extract with cut lengths was not exported for ES26-080.
A38: 5.5 | B38: Floor-noggin blockers (FF partition lines on / beside doubled trimmers) and 6 ceiling-noggin blockers on the bungalow hip set - detail with the floor / truss designers.
A39: 5.6 | B39: Room areas agree with the drawn areas within ~0.4 m2 (finished faces from the ICF set-out on the drawn outer face) - see Schedule A.
A41: 6 What IS in the Nudura price (Quotation ES26-080)
A42: 6.1 | B42: Nudura pre-cut ICF kit for the 8 blocks / 18 plots as modelled in the BuildEase Design Suite (stepped footings per block).
A43: 6.2 | B43: Accessories: VJC clips, fibre tape, protective tape, spray foam, Form Lock and T-junction straps, end caps and lintel closures.
A44: 6.3 | B44: BuildEase Pre-Cut Service: design, coordination, installation drawings, pre-cutting and packaging of forms, field services support.
A45: 6.4 | B45: Nothing in Bills 1 to 5 of this package is included in the Nudura price.
A47: 7 Pricing instructions to tenderers
A48: 7.1 | B48: Each bill item has a SUPPLY rate and an INSTALL rate. Insert rates only in the pale-yellow cells of the Excel workbook: Supply = Site total qty x Supply rate; Install = Site total qty x Install rate; Line total = Supply + Install. Items measured as "item" are lump sums: the rate entered is the amount.
A49: 7.2 | B49: Each bill ends with a Package Summary (section subtotals for Supply / Install / Total and the package total). The Cover carries the full overview: one row per bill, grand totals, optional Preliminaries, Overheads & profit and Contingency percentages (pale-yellow cells; blank = 0) and the ICF package hook.
A50: 7.3 | B50: All other cells are locked by sheet protection (no password - Review > Unprotect Sheet if a change is genuinely needed) so formulas cannot be overwritten by accident.
A51: 7.4 | B51: Re-measure and verify all quantities before pricing or ordering. State any qualification against the item in the Notes column.
A52: 7.5 | B52: The Order guide figures and Schedules A to D are not measured bill items and must not be priced as such. All amounts exclude VAT.

Sheet Summary of Bills
C1: Summary of Bills - section breakdown
C2: ES26-080 | Land to Rear of 1-8 Wesley Terrace, Castleside | Wannop Developments Ltd - amounts by others, excl. VAT
A4: DISCLAIMER: This information is supplied in good faith for guidance and coordination only. It is not part of the Nudura ICF price and must be checked and verified by the appropriate professional (quantity surveyor, designer, engineer or supplier) before use. Only the Nudura ICF formwork and associated accessories are included in our price. Quantities are measured from the quotation models and the SK11A drawings (DRAFT); no allowance for waste is included unless stated. Quantities are per block for each block type; the Site total multiplies by the number of blocks. Rates and amounts are by others.
A6: Bill | B6: Section | C6: Description | D6: Supply £ | E6: Install £ | F6: Total £
A7: 1 | B7: 1A | C7: Brick slip system over ICF - units 01-15 (NRM2 21 / package CLD) | D7: ='Bill 1 External Finishes'!K40 | E7: ='Bill 1 External Finishes'!L40 | F7: ='Bill 1 External Finishes'!M40
A8: 1 | B8: 1B | C8: Stone slip / thin stone veneer system over ICF - units 16-18, block B08 (NRM2 21 / package CLD) | D8: ='Bill 1 External Finishes'!K41 | E8: ='Bill 1 External Finishes'!L41 | F8: ='Bill 1 External Finishes'!M41
A9: 1 | B9: 1C | C9: Sloping plots - finishes and protection below DPC (PROVISIONAL; NRM2 21 / 17) | D9: ='Bill 1 External Finishes'!K42 | E9: ='Bill 1 External Finishes'!L42 | F9: ='Bill 1 External Finishes'!M42
A10: 1 | B10: 1D | C10: Coordination items (supply by others) | D10: ='Bill 1 External Finishes'!K43 | E10: ='Bill 1 External Finishes'!L43 | F10: ='Bill 1 External Finishes'!M43
A11: Bill 1 - External Wall Finishes - Brick & Stone Slips (package CLD) | D11: ='Bill 1 External Finishes'!K44 | E11: ='Bill 1 External Finishes'!L44 | F11: ='Bill 1 External Finishes'!M44
A12: 2 | B12: 2A | C12: Plasterboard wall linings (NRM2 28 / package DRY) | D12: ='Bill 2 Internal Linings'!K37 | E12: ='Bill 2 Internal Linings'!L37 | F12: ='Bill 2 Internal Linings'!M37
A13: 2 | B13: 2B | C13: Plasterboard ceilings (NRM2 28 / package DRY) | D13: ='Bill 2 Internal Linings'!K38 | E13: ='Bill 2 Internal Linings'!L38 | F13: ='Bill 2 Internal Linings'!M38
A14: 2 | B14: 2C | C14: Jointing, beads and skim (NRM2 28 / package DRY) | D14: ='Bill 2 Internal Linings'!K39 | E14: ='Bill 2 Internal Linings'!L39 | F14: ='Bill 2 Internal Linings'!M39
A15: Bill 2 - Internal Linings - Plasterboard, Tape, Beads & Skim (package DRY) | D15: ='Bill 2 Internal Linings'!K40 | E15: ='Bill 2 Internal Linings'!L40 | F15: ='Bill 2 Internal Linings'!M40
A16: 3 | B16: 3A | C16: Internal doorsets (NRM2 24 / package JOI) | D16: ='Bill 3 Doors'!K28 | E16: ='Bill 3 Doors'!L28 | F16: ='Bill 3 Doors'!M28
A17: 3 | B17: 3B | C17: Ironmongery (NRM2 24 / package JOI) | D17: ='Bill 3 Doors'!K29 | E17: ='Bill 3 Doors'!L29 | F17: ='Bill 3 Doors'!M29
A18: 3 | B18: 3C | C18: External doorsets and windows (for information - supply by the window / door package) | D18: ='Bill 3 Doors'!K30 | E18: ='Bill 3 Doors'!L30 | F18: ='Bill 3 Doors'!M30
A19: Bill 3 - Internal Doors & Ironmongery (package JOI) | D19: ='Bill 3 Doors'!K31 | E19: ='Bill 3 Doors'!L31 | F19: ='Bill 3 Doors'!M31
A20: 4 | B20: 4A | C20: Skirtings (NRM2 22 / package JOI) | D20: ='Bill 4 Joinery'!K40 | E20: ='Bill 4 Joinery'!L40 | F20: ='Bill 4 Joinery'!M40
A21: 4 | B21: 4B | C21: Architraves (NRM2 22 / package JOI) | D21: ='Bill 4 Joinery'!K41 | E21: ='Bill 4 Joinery'!L41 | F21: ='Bill 4 Joinery'!M41
A22: 4 | B22: 4C | C22: Window boards (NRM2 22 / package JOI) | D22: ='Bill 4 Joinery'!K42 | E22: ='Bill 4 Joinery'!L42 | F22: ='Bill 4 Joinery'!M42
A23: 4 | B23: 4D | C23: Loft access (NRM2 22 / package JOI) | D23: ='Bill 4 Joinery'!K43 | E23: ='Bill 4 Joinery'!L43 | F23: ='Bill 4 Joinery'!M43
A24: Bill 4 - Joinery - Skirtings, Architraves, Window Boards & Loft Hatches (package JOI) | D24: ='Bill 4 Joinery'!K44 | E24: ='Bill 4 Joinery'!L44 | F24: ='Bill 4 Joinery'!M44
A25: 5 | B25: 5A | C25: Timber stud partitions, non-loadbearing - framing (NRM2 16 / package JOI) | D25: ='Bill 5 Partitions'!K42 | E25: ='Bill 5 Partitions'!L42 | F25: ='Bill 5 Partitions'!M42
A26: 5 | B26: 5B | C26: Partition timber - supply (NRM2 16 / package JOI) | D26: ='Bill 5 Partitions'!K43 | E26: ='Bill 5 Partitions'!L43 | F26: ='Bill 5 Partitions'!M43
A27: 5 | B27: 5C | C27: Forming door openings in partitions (NRM2 16 / package JOI) | D27: ='Bill 5 Partitions'!K44 | E27: ='Bill 5 Partitions'!L44 | F27: ='Bill 5 Partitions'!M44
A28: 5 | B28: 5D | C28: Pattresses, noggins to floor and roof structure, head restraint (NRM2 16 / package JOI) | D28: ='Bill 5 Partitions'!K45 | E28: ='Bill 5 Partitions'!L45 | F28: ='Bill 5 Partitions'!M45
A29: 5 | B29: 5E | C29: Fixings and sundries (NRM2 16 / package JOI) | D29: ='Bill 5 Partitions'!K46 | E29: ='Bill 5 Partitions'!L46 | F29: ='Bill 5 Partitions'!M46
A30: Bill 5 - Timber Stud Partitions - Framing, Openings, Pattresses & Fixings (package JOI) | D30: ='Bill 5 Partitions'!K47 | E30: ='Bill 5 Partitions'!L47 | F30: ='Bill 5 Partitions'!M47
A31: TOTAL - finishes / ancillary trades, net (agrees with the Cover overview) | D31: =D11+D15+D19+D24+D30 | E31: =E11+E15+E19+E24+E30 | F31: =F11+F15+F19+F24+F30
A33: Schedules A to D are reference schedules and are not priced. Preliminaries, overheads & profit, contingency and the ICF package (BuildEase BOQ Builder) are applied on the Cover.

Sheet Bill 1 External Finishes
C1: Bill 1 - External Wall Finishes - Brick & Stone Slips
C2: Finishes applied to the outer face of the ICF walls: brick slips to units 01-15, stone slips to units 16-18 (SK11A). [NRM2 21 / package CLD]
A4: DISCLAIMER: This information is supplied in good faith for guidance and coordination only. It is not part of the Nudura ICF price and must be checked and verified by the appropriate professional (quantity surveyor, designer, engineer or supplier) before use. Only the Nudura ICF formwork and associated accessories are included in our price. Quantities are measured from the quotation models and the SK11A drawings (DRAFT); no allowance for waste is included unless stated. Quantities are per block for each block type; the Site total multiplies by the number of blocks. Rates and amounts are by others.
A6: Ref | B6: Description | C6: Unit | D6: T01_SEMI per block | E6: T01_TER3 brick per block | F6: T01_TER3 stone per block | G6: T02_BUNG per block | H6: Site total qty | I6: Supply rate £ | J6: Install rate £ | K6: Supply £ | L6: Install £ | M6: Line total £ | N6: Notes
B7: Number of blocks of each type (Site total = per-block qty x blocks) | D7: 2 | E7: 3 | F7: 1 | G7: 2 | H7: =SUM(D7:G7) | N7: Blocks: T01_SEMI = B01, B04 (plots 01-02, 09-10); T01_TER3 brick = B02, B03, B05 (plots 03-08, 11-13); T01_TER3 stone = B08 (plots 16-18); T02_BUNG = B06, B07 (plots 14, 15)
A8: 1A Brick slip system over ICF - units 01-15 (NRM2 21 / package CLD)
B9: Brick slip system applied to the outer EPS face of the Nudura ICF (e.g. adhesive-fixed slips on a reinforced base coat, or a rail / board system - product, colour and fixing to match the SK11A brick and to be confirmed with the system supplier). Measured net of structural openings from DPC (FFL - 150) to the eaves soffit (5,320 HT01 / 2,320 HT02) and the gable rake to the drawn brick apex (8,255).
A10: 1A.1 | B10: Brick slips to walls, Front elevation, net of openings | C10: m2 | D10: 48.513 | E10: 71.676 | G10: 21.997 | H10: =SUMPRODUCT($D$7:$G$7,D10:G10) | K10: =N(H10)*N(I10) | L10: =N(H10)*N(J10) | M10: =K10+L10 | N10: Order guide +10% = 391.7; DPC (FFL-150) to eaves / verge
A11: 1A.2 | B11: Brick slips to walls, Rear elevation, net of openings | C11: m2 | D11: 47.982 | E11: 70.88 | G11: 17.006 | H11: =SUMPRODUCT($D$7:$G$7,D11:G11) | K11: =N(H11)*N(I11) | L11: =N(H11)*N(J11) | M11: =K11+L11 | N11: Order guide +10% = 376.9; DPC (FFL-150) to eaves / verge
A12: 1A.3 | B12: Brick slips to walls, Gable elevations (end units, incl. gable triangle to the drawn apex), net of openings | C12: m2 | D12: 138.056 | E12: 138.056 | H12: =SUMPRODUCT($D$7:$G$7,D12:G12) | K12: =N(H12)*N(I12) | L12: =N(H12)*N(J12) | M12: =K12+L12 | N12: Order guide +10% = 759.3; DPC (FFL-150) to eaves / verge
A13: 1A.4 | B13: Brick slips to walls, Side elevations (bungalow, hipped roof), net of openings | C13: m2 | G13: 35.815 | H13: =SUMPRODUCT($D$7:$G$7,D13:G13) | K13: =N(H13)*N(I13) | L13: =N(H13)*N(J13) | M13: =K13+L13 | N13: Order guide +10% = 78.8; DPC (FFL-150) to eaves / verge
A14: 1A.5 | B14: Brick slips to reveal returns, jambs and heads, 144 mm girth (frame set back 1/3) | C14: m2 | D14: 9.439 | E14: 14.158 | G14: 4.948 | H14: =SUMPRODUCT($D$7:$G$7,D14:G14) | K14: =N(H14)*N(I14) | L14: =N(H14)*N(J14) | M14: =K14+L14 | N14: Order guide +10% = 78.4
A15: 1A.6 | B15: Brick corner (L-shaped) slips, building external corners | C15: m | D15: 21.88 | E15: 21.88 | G15: 9.88 | H15: =SUMPRODUCT($D$7:$G$7,D15:G15) | K15: =N(H15)*N(I15) | L15: =N(H15)*N(J15) | M15: =K15+L15 | N15: Order guide +5% = 135.6
A16: 1A.7 | B16: Brick corner slips / reveal returns at window and door jambs and heads | C16: m | D16: 65.76 | E16: 98.64 | G16: 34.47 | H16: =SUMPRODUCT($D$7:$G$7,D16:G16) | K16: =N(H16)*N(I16) | L16: =N(H16)*N(J16) | M16: =K16+L16 | N16: Order guide +5% = 521.2
A17: 1A.8 | B17: Base support rail / starter track at DPC level, incl. weep / drip detail | C17: m | D17: 43.4 | E17: 54.75 | G17: 38.6 | H17: =SUMPRODUCT($D$7:$G$7,D17:G17) | K17: =N(H17)*N(I17) | L17: =N(H17)*N(J17) | M17: =K17+L17 | N17: Order guide +10% = 361.1
A18: 1A.9 | B18: Head closure / stop trim at eaves soffit and along the gable verge rake | C18: m | D18: 46.479 | E18: 57.829 | G18: 38.6 | H18: =SUMPRODUCT($D$7:$G$7,D18:G18) | K18: =N(H18)*N(I18) | L18: =N(H18)*N(J18) | M18: =K18+L18 | N18: Order guide +10% = 378.0
A19: 1A.10 | B19: Vertical movement joint at each party-wall line, front and rear faces, full height: backer rod and sealant | C19: m | D19: 10.94 | E19: 21.88 | H19: =SUMPRODUCT($D$7:$G$7,D19:G19) | K19: =N(H19)*N(I19) | L19: =N(H19)*N(J19) | M19: =K19+L19 | N19: Positions / spacing to the slip-system supplier (add intermediate joints if required)
A20: 1B Stone slip / thin stone veneer system over ICF - units 16-18, block B08 (NRM2 21 / package CLD)
B21: Natural or reconstituted stone slip (thin veneer) system to match the SK11A stone elevations for units 16-18 (block B08), adhesive or rail fixed over the ICF EPS face. Product, coursing, weight and fixing to be confirmed with the supplier and the structural engineer. Measured as 1A.
A22: 1B.1 | B22: Stone slips to walls, Front elevation, net of openings | C22: m2 | F22: 71.676 | H22: =SUMPRODUCT($D$7:$G$7,D22:G22) | K22: =N(H22)*N(I22) | L22: =N(H22)*N(J22) | M22: =K22+L22 | N22: Order guide +10% = 78.8; DPC (FFL-150) to eaves / verge
A23: 1B.2 | B23: Stone slips to walls, Rear elevation, net of openings | C23: m2 | F23: 70.88 | H23: =SUMPRODUCT($D$7:$G$7,D23:G23) | K23: =N(H23)*N(I23) | L23: =N(H23)*N(J23) | M23: =K23+L23 | N23: Order guide +10% = 78.0; DPC (FFL-150) to eaves / verge
A24: 1B.3 | B24: Stone slips to walls, Gable elevations (end units, incl. gable triangle to the drawn apex), net of openings | C24: m2 | F24: 138.056 | H24: =SUMPRODUCT($D$7:$G$7,D24:G24) | K24: =N(H24)*N(I24) | L24: =N(H24)*N(J24) | M24: =K24+L24 | N24: Order guide +10% = 151.9; DPC (FFL-150) to eaves / verge
A25: 1B.4 | B25: Stone slips to reveal returns, jambs and heads, 149 mm girth (frame set back 1/3) | C25: m2 | F25: 14.651 | H25: =SUMPRODUCT($D$7:$G$7,D25:G25) | K25: =N(H25)*N(I25) | L25: =N(H25)*N(J25) | M25: =K25+L25 | N25: Order guide +10% = 16.1
A26: 1B.5 | B26: Stone corner (L-shaped) slips, building external corners | C26: m | F26: 21.88 | H26: =SUMPRODUCT($D$7:$G$7,D26:G26) | K26: =N(H26)*N(I26) | L26: =N(H26)*N(J26) | M26: =K26+L26 | N26: Order guide +5% = 23.0
A27: 1B.6 | B27: Stone corner slips / reveal returns at window and door jambs and heads | C27: m | F27: 98.64 | H27: =SUMPRODUCT($D$7:$G$7,D27:G27) | K27: =N(H27)*N(I27) | L27: =N(H27)*N(J27) | M27: =K27+L27 | N27: Order guide +5% = 103.6
A28: 1B.7 | B28: Base support rail / starter track at DPC level, incl. weep / drip detail | C28: m | F28: 54.75 | H28: =SUMPRODUCT($D$7:$G$7,D28:G28) | K28: =N(H28)*N(I28) | L28: =N(H28)*N(J28) | M28: =K28+L28 | N28: Order guide +10% = 60.2
A29: 1B.8 | B29: Head closure / stop trim at eaves soffit and along the gable verge rake | C29: m | F29: 57.829 | H29: =SUMPRODUCT($D$7:$G$7,D29:G29) | K29: =N(H29)*N(I29) | L29: =N(H29)*N(J29) | M29: =K29+L29 | N29: Order guide +10% = 63.6
A30: 1B.9 | B30: Vertical movement joint at each party-wall line, front and rear faces, full height: backer rod and sealant | C30: m | F30: 21.88 | H30: =SUMPRODUCT($D$7:$G$7,D30:G30) | K30: =N(H30)*N(I30) | L30: =N(H30)*N(J30) | M30: =K30+L30 | N30: Positions / spacing to the slip-system supplier (add intermediate joints if required)
A31: 1C Sloping plots - finishes and protection below DPC (PROVISIONAL; NRM2 21 / 17)
B32: From the existing survey levels at each block corner (10G) and the stepped-footing rule FFL = mean corner ground + 150. Final external levels are not designed - re-measure on the engineer's / architect's finished levels. Per-block figures in Schedule D.
A33: 1C.1 | B33: Exposed ICF face between DPC and existing ground on the low (fill) side: continue the slip finish down to finished ground (or below-DPC plinth finish / protection board) | C33: m2 | H33: 83.31 | K33: =N(H33)*N(I33) | L33: =N(H33)*N(J33) | M33: =K33+L33 | N33: B01 9.7; B02 8.9; B03 15.1; B04 2.7; B05 16.4; B06 6.1; B07 9.5; B08 14.9
A34: 1C.2 | B34: Ground above DPC against the ICF on the high (cut) side: waterproofing / tanking to the ICF face, protection board and perimeter drainage - or regrade to 150 below DPC | C34: m2 | H34: 83.31 | K34: =N(H34)*N(I34) | L34: =N(H34)*N(J34) | M34: =K34+L34 | N34: B01 9.7; B02 8.9; B03 15.1; B04 2.7; B05 16.4; B06 6.1; B07 9.5; B08 14.9
A35: 1D Coordination items (supply by others)
A36: 1D.1 | B36: External window cills, measured at structural opening width (for coordination with the window package) | C36: m | D36: 14.52 | E36: 21.78 | F36: 21.78 | G36: 6.24 | H36: =SUMPRODUCT($D$7:$G$7,D36:G36) | K36: =N(H36)*N(I36) | L36: =N(H36)*N(J36) | M36: =K36+L36 | N36: By window supplier - coordination only
A38: PACKAGE SUMMARY - Bill 1 External Wall Finishes - Brick & Stone Slips (package CLD; amounts by others, excl. VAT)
A39: Section | B39: Description | K39: Supply £ | L39: Install £ | M39: Total £
A40: 1A | B40: Brick slip system over ICF - units 01-15 (NRM2 21 / package CLD) | K40: =SUM(K9:K19) | L40: =SUM(L9:L19) | M40: =SUM(M9:M19)
A41: 1B | B41: Stone slip / thin stone veneer system over ICF - units 16-18, block B08 (NRM2 21 / package CLD) | K41: =SUM(K21:K30) | L41: =SUM(L21:L30) | M41: =SUM(M21:M30)
A42: 1C | B42: Sloping plots - finishes and protection below DPC (PROVISIONAL; NRM2 21 / 17) | K42: =SUM(K32:K34) | L42: =SUM(L32:L34) | M42: =SUM(M32:M34)
A43: 1D | B43: Coordination items (supply by others) | K43: =SUM(K36:K36) | L43: =SUM(L36:L36) | M43: =SUM(M36:M36)
A44: PACKAGE TOTAL - Bill 1, carried to the Cover overview | K44: =SUM(K40:K43) | L44: =SUM(L40:L43) | M44: =SUM(M40:M43)
A45: Pale-yellow cells are the only inputs (Supply rate, Install rate). Amounts, subtotals and totals are formulas; the sheet is protected without a password (Review > Unprotect Sheet). Amounts exclude VAT and are NOT part of the Nudura ICF price.

Sheet Bill 2 Internal Linings
C1: Bill 2 - Internal Linings - Plasterboard, Tape, Beads & Skim
C2: Dry linings to the inside faces of the ICF walls, party walls, timber partitions, ceilings, reveals and stair. [NRM2 28 / package DRY]
A4: DISCLAIMER: This information is supplied in good faith for guidance and coordination only. It is not part of the Nudura ICF price and must be checked and verified by the appropriate professional (quantity surveyor, designer, engineer or supplier) before use. Only the Nudura ICF formwork and associated accessories are included in our price. Quantities are measured from the quotation models and the SK11A drawings (DRAFT); no allowance for waste is included unless stated. Quantities are per block for each block type; the Site total multiplies by the number of blocks. Rates and amounts are by others.
A6: Ref | B6: Description | C6: Unit | D6: T01_SEMI per block | E6: T01_TER3 brick per block | F6: T01_TER3 stone per block | G6: T02_BUNG per block | H6: Site total qty | I6: Supply rate £ | J6: Install rate £ | K6: Supply £ | L6: Install £ | M6: Line total £ | N6: Notes
B7: Number of blocks of each type (Site total = per-block qty x blocks) | D7: 2 | E7: 3 | F7: 1 | G7: 2 | H7: =SUM(D7:G7) | N7: Blocks: T01_SEMI = B01, B04 (plots 01-02, 09-10); T01_TER3 brick = B02, B03, B05 (plots 03-08, 11-13); T01_TER3 stone = B08 (plots 16-18); T02_BUNG = B06, B07 (plots 14, 15)
A8: 2A Plasterboard wall linings (NRM2 28 / package DRY)
B9: Measured net on the finished room faces, per unit and summed per block. Heights: HT01 GF 0 to u/s FF joists 2,425; HT01 FF deck 2,700 to u/s truss chords 5,370 (2,670); HT02 0 to u/s truss chords 2,336. Openings deducted (external openings once; internal door gaps on both faces). Board types are proposals - confirm with the board supplier; ICF faces need mechanical fixings into the webs.
A10: 2A.1 | B10: GF external walls - internal face of the ICF: 12.5 mm wallboard, adhesive dabs + mechanical fixings to the ICF webs (MR board in WC) | C10: m2 | D10: 74.938 | E10: 90.644 | F10: 90.644 | G10: 61.054 | H10: =SUMPRODUCT($D$7:$G$7,D10:G10) | K10: =N(H10)*N(I10) | L10: =N(H10)*N(J10) | M10: =K10+L10 | N10: Order guide +10% = 698.0
A11: 2A.2 | B11: FF external walls - internal face of the ICF (HT01): 12.5 mm wallboard as above (MR board in bathroom) | C11: m2 | D11: 91.816 | E11: 114.078 | F11: 114.078 | H11: =SUMPRODUCT($D$7:$G$7,D11:G11) | K11: =N(H11)*N(I11) | L11: =N(H11)*N(J11) | M11: =K11+L11 | N11: Order guide +10% = 703.9
A12: 2A.3 | B12: GF party walls (ICF 6in Std) - each house side: 15 mm sound / fire board on dabs per the ICF separating-wall detail (confirm robust detail) | C12: m2 | D12: 44.808 | E12: 89.037 | F12: 89.037 | H12: =SUMPRODUCT($D$7:$G$7,D12:G12) | K12: =N(H12)*N(I12) | L12: =N(H12)*N(J12) | M12: =K12+L12 | N12: Order guide +10% = 490.3
A13: 2A.4 | B13: FF party walls (ICF 6in Std) - each house side: 15 mm sound / fire board as above | C13: m2 | D13: 48.7 | E13: 96.764 | F13: 96.764 | H13: =SUMPRODUCT($D$7:$G$7,D13:G13) | K13: =N(H13)*N(I13) | L13: =N(H13)*N(J13) | M13: =K13+L13 | N13: Order guide +10% = 532.9
A14: 2A.5 | B14: GF timber stud partitions - both faces: 15 mm board on 38 x 89 studs (119 build-up); MR in wet rooms | C14: m2 | D14: 47.522 | E14: 71.406 | F14: 71.406 | G14: 95.627 | H14: =SUMPRODUCT($D$7:$G$7,D14:G14) | K14: =N(H14)*N(I14) | L14: =N(H14)*N(J14) | M14: =K14+L14 | N14: Order guide +10% = 629.1
A15: 2A.6 | B15: FF timber stud partitions - both faces: 15 mm board on 38 x 89 studs (119 build-up); MR in wet rooms | C15: m2 | D15: 178.146 | E15: 267.422 | F15: 267.422 | H15: =SUMPRODUCT($D$7:$G$7,D15:G15) | K15: =N(H15)*N(I15) | L15: =N(H15)*N(J15) | M15: =K15+L15 | N15: Order guide +10% = 1,568.6
A16: 2A.7 | B16: Under-stair spandrel / store closing panel - both faces (HT01): 12.5 mm board on 38 x 63 framing (framing by the stair installer) | C16: m2 | D16: 8.923 | E16: 13.446 | F16: 13.446 | H16: =SUMPRODUCT($D$7:$G$7,D16:G16) | K16: =N(H16)*N(I16) | L16: =N(H16)*N(J16) | M16: =K16+L16 | N16: Order guide +10% = 78.8
A17: 2A.8 | B17: Internal reveals to external windows and doors, jambs and heads, 195 mm deep: 12.5 mm board / bonding and skim | C17: m2 | D17: 12.795 | E17: 19.192 | F17: 19.192 | G17: 6.707 | H17: =SUMPRODUCT($D$7:$G$7,D17:G17) | K17: =N(H17)*N(I17) | L17: =N(H17)*N(J17) | M17: =K17+L17 | N17: Order guide +10% = 127.3
A18: 2A.9 | B18: Stair-well floor-zone band (2,425-2,700) on the well side and end walls: 12.5 mm board | C18: m2 | D18: 2.141 | E18: 3.211 | F18: 3.211 | H18: =SUMPRODUCT($D$7:$G$7,D18:G18) | K18: =N(H18)*N(I18) | L18: =N(H18)*N(J18) | M18: =K18+L18 | N18: HT01 only
A19: 2B Plasterboard ceilings (NRM2 28 / package DRY)
B20: Net plan areas of the rooms. HT01 GF ceiling is the u/s of the FF metal-web joist floor (internal floor, Part E: 40 dB - mineral wool in the joist zone is excluded); stair well deducted. Top-floor ceilings under the trusses carry a VCL. Multiply by layers for board.
A21: 2B.1 | B21: HT01 GF ceilings, u/s FF joists (2,425): 12.5 mm wallboard (15 mm if the fire strategy requires) | C21: m2 | D21: 92.079 | E21: 138.233 | F21: 138.233 | H21: =SUMPRODUCT($D$7:$G$7,D21:G21) | K21: =N(H21)*N(I21) | L21: =N(H21)*N(J21) | M21: =K21+L21 | N21: Order guide +10% = 810.8
A22: 2B.2 | B22: HT01 FF ceilings, u/s truss bottom chords (5,370), incl. landing over the stair well: 12.5 mm board + 500g VCL | C22: m2 | D22: 94.354 | E22: 141.645 | F22: 141.645 | H22: =SUMPRODUCT($D$7:$G$7,D22:G22) | K22: =N(H22)*N(I22) | L22: =N(H22)*N(J22) | M22: =K22+L22 | N22: Order guide +10% = 830.8
A23: 2B.3 | B23: HT02 ceilings, u/s truss bottom chords (2,336): 12.5 mm board + 500g VCL | C23: m2 | G23: 71.125 | H23: =SUMPRODUCT($D$7:$G$7,D23:G23) | K23: =N(H23)*N(I23) | L23: =N(H23)*N(J23) | M23: =K23+L23 | N23: Order guide +10% = 156.5
A24: 2B.4 | B24: Stair soffit lining, sloping (13 treads x 288 going, 1000 wide, 33.8 deg): 12.5 mm board | C24: m2 | D24: 9.012 | E24: 13.518 | F24: 13.518 | H24: =SUMPRODUCT($D$7:$G$7,D24:G24) | K24: =N(H24)*N(I24) | L24: =N(H24)*N(J24) | M24: =K24+L24 | N24: HT01 only; winders approximated as treads
A25: 2C Jointing, beads and skim (NRM2 28 / package DRY)
A26: 2C.1 | B26: Scrim tape, board joints (walls / 1.2 m; ceilings / 1.2 + 2.4 m) | C26: m | D26: 669.13 | E26: 1004.412 | F26: 1004.412 | G26: 225.063 | H26: =SUMPRODUCT($D$7:$G$7,D26:G26) | K26: =N(H26)*N(I26) | L26: =N(H26)*N(J26) | M26: =K26+L26 | N26: Order guide +10% = 6,386.6
A27: 2C.2 | B27: Scrim tape, internal angles wall to wall | C27: m | D27: 286.57 | E27: 431.19 | F27: 431.19 | G27: 84.096 | H27: =SUMPRODUCT($D$7:$G$7,D27:G27) | K27: =N(H27)*N(I27) | L27: =N(H27)*N(J27) | M27: =K27+L27 | N27: Order guide +10% = 2,712.7
A28: 2C.3 | B28: Scrim tape, wall to ceiling angles | C28: m | D28: 226.049 | E28: 339.276 | F28: 339.276 | G28: 85.028 | H28: =SUMPRODUCT($D$7:$G$7,D28:G28) | K28: =N(H28)*N(I28) | L28: =N(H28)*N(J28) | M28: =K28+L28 | N28: Order guide +10% = 2,177.2
A29: 2C.4 | B29: Angle / corner bead, external corners in rooms | C29: m | D29: 84.19 | E29: 127.62 | F29: 127.62 | G29: 23.36 | H29: =SUMPRODUCT($D$7:$G$7,D29:G29) | K29: =N(H29)*N(I29) | L29: =N(H29)*N(J29) | M29: =K29+L29 | N29: Order guide +10% = 798.1
A30: 2C.5 | B30: Angle bead, window and door reveals (jambs and heads) | C30: m | D30: 65.76 | E30: 98.64 | F30: 98.64 | G30: 34.47 | H30: =SUMPRODUCT($D$7:$G$7,D30:G30) | K30: =N(H30)*N(I30) | L30: =N(H30)*N(J30) | M30: =K30+L30 | N30: Order guide +10% = 654.5
A31: 2C.6 | B31: Skim coat, 2-3 mm, to all net wall, reveal and ceiling board faces | C31: m2 | D31: 705.233 | E31: 1058.596 | F31: 1058.596 | G31: 234.513 | H31: =SUMPRODUCT($D$7:$G$7,D31:G31) | K31: =N(H31)*N(I31) | L31: =N(H31)*N(J31) | M31: =K31+L31 | N31: Face layer only
A32: 2D Ordering guide (not a measured item)
A33: 2D.1 | B33: Plasterboard to purchase, all types, before waste | C33: m2 | D33: 705.233 | E33: 1058.596 | F33: 1058.596 | G33: 234.513 | H33: =SUMPRODUCT($D$7:$G$7,D33:G33) | M33: not priced | N33: Order guide +10% = 6,725.3 (guide only)
A35: PACKAGE SUMMARY - Bill 2 Internal Linings - Plasterboard, Tape, Beads & Skim (package DRY; amounts by others, excl. VAT)
A36: Section | B36: Description | K36: Supply £ | L36: Install £ | M36: Total £
A37: 2A | B37: Plasterboard wall linings (NRM2 28 / package DRY) | K37: =SUM(K9:K18) | L37: =SUM(L9:L18) | M37: =SUM(M9:M18)
A38: 2B | B38: Plasterboard ceilings (NRM2 28 / package DRY) | K38: =SUM(K20:K24) | L38: =SUM(L20:L24) | M38: =SUM(M20:M24)
A39: 2C | B39: Jointing, beads and skim (NRM2 28 / package DRY) | K39: =SUM(K26:K31) | L39: =SUM(L26:L31) | M39: =SUM(M26:M31)
A40: PACKAGE TOTAL - Bill 2, carried to the Cover overview | K40: =SUM(K37:K39) | L40: =SUM(L37:L39) | M40: =SUM(M37:M39)
A41: Pale-yellow cells are the only inputs (Supply rate, Install rate). Amounts, subtotals and totals are formulas; the sheet is protected without a password (Review > Unprotect Sheet). Amounts exclude VAT and are NOT part of the Nudura ICF price.

Sheet Bill 3 Doors
C1: Bill 3 - Internal Doors & Ironmongery
C2: Internal doorsets and ironmongery per block; external doorsets and windows listed for coordination only. [NRM2 24 / package JOI]
A4: DISCLAIMER: This information is supplied in good faith for guidance and coordination only. It is not part of the Nudura ICF price and must be checked and verified by the appropriate professional (quantity surveyor, designer, engineer or supplier) before use. Only the Nudura ICF formwork and associated accessories are included in our price. Quantities are measured from the quotation models and the SK11A drawings (DRAFT); no allowance for waste is included unless stated. Quantities are per block for each block type; the Site total multiplies by the number of blocks. Rates and amounts are by others.
A6: Ref | B6: Description | C6: Unit | D6: T01_SEMI per block | E6: T01_TER3 brick per block | F6: T01_TER3 stone per block | G6: T02_BUNG per block | H6: Site total qty | I6: Supply rate £ | J6: Install rate £ | K6: Supply £ | L6: Install £ | M6: Line total £ | N6: Notes
B7: Number of blocks of each type (Site total = per-block qty x blocks) | D7: 2 | E7: 3 | F7: 1 | G7: 2 | H7: =SUM(D7:G7) | N7: Blocks: T01_SEMI = B01, B04 (plots 01-02, 09-10); T01_TER3 brick = B02, B03, B05 (plots 03-08, 11-13); T01_TER3 stone = B08 (plots 16-18); T02_BUNG = B06, B07 (plots 14, 15)
A8: 3A Internal doorsets (NRM2 24 / package JOI)
B9: From the plan door gaps (WD_partitions.json, 140 site-wide): 900 gap -> 826 x 2040 leaf; 800 -> 726; 700 -> 626. Linings 32 x 132 (119 partition + 13). Two-storey houses and bungalows: no fire doors required (no floor over 4.5 m, ADB Vol 1). Pre-hung doorsets or leaf + lining + stops; finish / style by the client.
A10: 3A.1 | B10: Internal doorset, 626 x 2040 x 35 leaf, 32 x 132 lining set, stops, cupboard / store | C10: nr | D10: 6 | E10: 9 | F10: 9 | H10: =SUMPRODUCT($D$7:$G$7,D10:G10) | K10: =N(H10)*N(I10) | L10: =N(H10)*N(J10) | M10: =K10+L10 | N10: cupboard - landing; open-plan living - under-stair store
A11: 3A.2 | B11: Internal doorset, 726 x 2040 x 35 leaf, 32 x 132 lining set, stops, cupboard / store | C11: nr | G11: 3 | H11: =SUMPRODUCT($D$7:$G$7,D11:G11) | K11: =N(H11)*N(I11) | L11: =N(H11)*N(J11) | M11: =K11+L11 | N11: bedroom 1 - cupboard; bedroom 2 - cupboard; cupboard - open-plan living
A12: 3A.3 | B12: Internal doorset, 826 x 2040 x 35 leaf, 32 x 132 lining set, stops, bathroom / WC | C12: nr | D12: 4 | E12: 6 | F12: 6 | G12: 1 | H12: =SUMPRODUCT($D$7:$G$7,D12:G12) | K12: =N(H12)*N(I12) | L12: =N(H12)*N(J12) | M12: =K12+L12 | N12: bathroom - landing; bathroom - open-plan living; open-plan living - wc
A13: 3A.4 | B13: Internal doorset, 826 x 2040 x 35 leaf, 32 x 132 lining set, stops, habitable rooms | C13: nr | D13: 6 | E13: 9 | F13: 9 | G13: 2 | H13: =SUMPRODUCT($D$7:$G$7,D13:G13) | K13: =N(H13)*N(I13) | L13: =N(H13)*N(J13) | M13: =K13+L13 | N13: bedroom 1 - landing; bedroom 1 - open-plan living; bedroom 2 - landing; bedroom 2 - open-plan living; bedroom 3 - landing
A14: 3B Ironmongery (NRM2 24 / package JOI)
A15: 3B.1 | B15: Butt hinges, 100 mm, pairs (1.5 pair per leaf) | C15: pr | D15: 24 | E15: 36 | F15: 36 | G15: 9 | H15: =SUMPRODUCT($D$7:$G$7,D15:G15) | K15: =N(H15)*N(I15) | L15: =N(H15)*N(J15) | M15: =K15+L15 | N15: 1.5 pr per leaf
A16: 3B.2 | B16: Standard sets: tubular latch, lever pair on roses | C16: set | D16: 6 | E16: 9 | F16: 9 | G16: 2 | H16: =SUMPRODUCT($D$7:$G$7,D16:G16) | K16: =N(H16)*N(I16) | L16: =N(H16)*N(J16) | M16: =K16+L16
A17: 3B.3 | B17: Bathroom / WC sets: privacy lock, thumb-turn with emergency release, lever pair | C17: set | D17: 4 | E17: 6 | F17: 6 | G17: 1 | H17: =SUMPRODUCT($D$7:$G$7,D17:G17) | K17: =N(H17)*N(I17) | L17: =N(H17)*N(J17) | M17: =K17+L17
A18: 3B.4 | B18: Cupboard sets PER LEAF: magnetic / roller catch and pull handle | C18: set | D18: 6 | E18: 9 | F18: 9 | G18: 3 | H18: =SUMPRODUCT($D$7:$G$7,D18:G18) | K18: =N(H18)*N(I18) | L18: =N(H18)*N(J18) | M18: =K18+L18 | N18: Per leaf (Tom 19.10)
A19: 3B.5 | B19: Door stops, floor or skirting mounted | C19: nr | D19: 16 | E19: 24 | F19: 24 | G19: 6 | H19: =SUMPRODUCT($D$7:$G$7,D19:G19) | K19: =N(H19)*N(I19) | L19: =N(H19)*N(J19) | M19: =K19+L19 | N19: One per leaf
B20: Flush bolts (one per double / pair door, fixed leaf): 0 - no pair doors on ES26-080 (all gaps <= 900).
A21: 3C External doorsets and windows (for information - supply by the window / door package)
A22: 3C.1 | B22: Front entrance doorset, composite, 1,110 x 2,100 structural opening, multi-point lock, PAS 24 / SBD | C22: nr | D22: 2 | E22: 3 | F22: 3 | G22: 1 | H22: =SUMPRODUCT($D$7:$G$7,D22:G22) | K22: =N(H22)*N(I22) | L22: =N(H22)*N(J22) | M22: =K22+L22 | N22: Coordination only
A23: 3C.2 | B23: Rear bifold doorset, 3-leaf, 2,610 x 2,100 structural opening, low threshold, PAS 24 | C23: nr | D23: 2 | E23: 3 | F23: 3 | G23: 2 | H23: =SUMPRODUCT($D$7:$G$7,D23:G23) | K23: =N(H23)*N(I23) | L23: =N(H23)*N(J23) | M23: =K23+L23 | N23: Coordination only
A24: 3C.3 | B24: Windows, uPVC casement (sizes in Schedule B) | C24: nr | D24: 12 | E24: 18 | F24: 18 | G24: 4 | H24: =SUMPRODUCT($D$7:$G$7,D24:G24) | K24: =N(H24)*N(I24) | L24: =N(H24)*N(J24) | M24: =K24+L24 | N24: Coordination only
A26: PACKAGE SUMMARY - Bill 3 Internal Doors & Ironmongery (package JOI; amounts by others, excl. VAT)
A27: Section | B27: Description | K27: Supply £ | L27: Install £ | M27: Total £
A28: 3A | B28: Internal doorsets (NRM2 24 / package JOI) | K28: =SUM(K9:K13) | L28: =SUM(L9:L13) | M28: =SUM(M9:M13)
A29: 3B | B29: Ironmongery (NRM2 24 / package JOI) | K29: =SUM(K15:K20) | L29: =SUM(L15:L20) | M29: =SUM(M15:M20)
A30: 3C | B30: External doorsets and windows (for information - supply by the window / door package) | K30: =SUM(K22:K24) | L30: =SUM(L22:L24) | M30: =SUM(M22:M24)
A31: PACKAGE TOTAL - Bill 3, carried to the Cover overview | K31: =SUM(K28:K30) | L31: =SUM(L28:L30) | M31: =SUM(M28:M30)
A32: Pale-yellow cells are the only inputs (Supply rate, Install rate). Amounts, subtotals and totals are formulas; the sheet is protected without a password (Review > Unprotect Sheet). Amounts exclude VAT and are NOT part of the Nudura ICF price.

Sheet Bill 4 Joinery
C1: Bill 4 - Joinery - Skirtings, Architraves, Window Boards & Loft Hatches
C2: Second-fix joinery measured per room and per opening. [NRM2 22 / package JOI]
A4: DISCLAIMER: This information is supplied in good faith for guidance and coordination only. It is not part of the Nudura ICF price and must be checked and verified by the appropriate professional (quantity surveyor, designer, engineer or supplier) before use. Only the Nudura ICF formwork and associated accessories are included in our price. Quantities are measured from the quotation models and the SK11A drawings (DRAFT); no allowance for waste is included unless stated. Quantities are per block for each block type; the Site total multiplies by the number of blocks. Rates and amounts are by others.
A6: Ref | B6: Description | C6: Unit | D6: T01_SEMI per block | E6: T01_TER3 brick per block | F6: T01_TER3 stone per block | G6: T02_BUNG per block | H6: Site total qty | I6: Supply rate £ | J6: Install rate £ | K6: Supply £ | L6: Install £ | M6: Line total £ | N6: Notes
B7: Number of blocks of each type (Site total = per-block qty x blocks) | D7: 2 | E7: 3 | F7: 1 | G7: 2 | H7: =SUM(D7:G7) | N7: Blocks: T01_SEMI = B01, B04 (plots 01-02, 09-10); T01_TER3 brick = B02, B03, B05 (plots 03-08, 11-13); T01_TER3 stone = B08 (plots 16-18); T02_BUNG = B06, B07 (plots 14, 15)
A8: 4A Skirtings (NRM2 22 / package JOI)
B9: Room floor perimeter on walls less every door opening into the room; stair-well edges (balustrade) and the wall beside the GF flight excluded. 18 x 94 MDF / softwood (profile by the client).
A10: 4A.1 | B10: Skirting: HT01 GF, Living / kitchen / dining (open plan, incl. hall and stair) | C10: m | D10: 44.564 | E10: 66.903 | F10: 66.903 | H10: =SUMPRODUCT($D$7:$G$7,D10:G10) | K10: =N(H10)*N(I10) | L10: =N(H10)*N(J10) | M10: =K10+L10
A11: 4A.2 | B11: Skirting: HT01 GF, Under-stair store | C11: m | D11: 8.41 | E11: 12.627 | F11: 12.627 | H11: =SUMPRODUCT($D$7:$G$7,D11:G11) | K11: =N(H11)*N(I11) | L11: =N(H11)*N(J11) | M11: =K11+L11
A12: 4A.3 | B12: Skirting: HT01 GF, WC | C12: m | D12: 10.359 | E12: 15.564 | F12: 15.564 | H12: =SUMPRODUCT($D$7:$G$7,D12:G12) | K12: =N(H12)*N(I12) | L12: =N(H12)*N(J12) | M12: =K12+L12
A13: 4A.4 | B13: Skirting: HT01 FF, Bedroom 1 | C13: m | D13: 28.958 | E13: 43.437 | F13: 43.437 | H13: =SUMPRODUCT($D$7:$G$7,D13:G13) | K13: =N(H13)*N(I13) | L13: =N(H13)*N(J13) | M13: =K13+L13
A14: 4A.5 | B14: Skirting: HT01 FF, Bedroom 2 | C14: m | D14: 29.344 | E14: 44.016 | F14: 44.016 | H14: =SUMPRODUCT($D$7:$G$7,D14:G14) | K14: =N(H14)*N(I14) | L14: =N(H14)*N(J14) | M14: =K14+L14
A15: 4A.6 | B15: Skirting: HT01 FF, Bedroom 3 | C15: m | D15: 21.999 | E15: 33.024 | F15: 33.024 | H15: =SUMPRODUCT($D$7:$G$7,D15:G15) | K15: =N(H15)*N(I15) | L15: =N(H15)*N(J15) | M15: =K15+L15
A16: 4A.7 | B16: Skirting: HT01 FF, Landing (incl. stair well) | C16: m | D16: 5.887 | E16: 8.855 | F16: 8.855 | H16: =SUMPRODUCT($D$7:$G$7,D16:G16) | K16: =N(H16)*N(I16) | L16: =N(H16)*N(J16) | M16: =K16+L16
A17: 4A.8 | B17: Skirting: HT01 FF, Cupboard / store | C17: m | D17: 8.972 | E17: 13.484 | F17: 13.484 | H17: =SUMPRODUCT($D$7:$G$7,D17:G17) | K17: =N(H17)*N(I17) | L17: =N(H17)*N(J17) | M17: =K17+L17
A18: 4A.9 | B18: Skirting: HT01 FF, Bathroom | C18: m | D18: 14.009 | E18: 21.039 | F18: 21.039 | H18: =SUMPRODUCT($D$7:$G$7,D18:G18) | K18: =N(H18)*N(I18) | L18: =N(H18)*N(J18) | M18: =K18+L18
A19: 4A.10 | B19: Skirting: HT02 GF, Bedroom 2 | C19: m | G19: 12.103 | H19: =SUMPRODUCT($D$7:$G$7,D19:G19) | K19: =N(H19)*N(I19) | L19: =N(H19)*N(J19) | M19: =K19+L19
A20: 4A.11 | B20: Skirting: HT02 GF, Storage | C20: m | G20: 4.093 | H20: =SUMPRODUCT($D$7:$G$7,D20:G20) | K20: =N(H20)*N(I20) | L20: =N(H20)*N(J20) | M20: =K20+L20
A21: 4A.12 | B21: Skirting: HT02 GF, Kitchen / dining / living (open plan, incl. entrance hall) | C21: m | G21: 25.937 | H21: =SUMPRODUCT($D$7:$G$7,D21:G21) | K21: =N(H21)*N(I21) | L21: =N(H21)*N(J21) | M21: =K21+L21
A22: 4A.13 | B22: Skirting: HT02 GF, Bedroom 1 | C22: m | G22: 12.053 | H22: =SUMPRODUCT($D$7:$G$7,D22:G22) | K22: =N(H22)*N(I22) | L22: =N(H22)*N(J22) | M22: =K22+L22
A23: 4A.14 | B23: Skirting: HT02 GF, Bathroom | C23: m | G23: 9.512 | H23: =SUMPRODUCT($D$7:$G$7,D23:G23) | K23: =N(H23)*N(I23) | L23: =N(H23)*N(J23) | M23: =K23+L23
A24: 4A.T | B24: Skirtings - total | C24: m | D24: =IF(SUM(D10:D23)=0,"",SUM(D10:D23)) | E24: =IF(SUM(E10:E23)=0,"",SUM(E10:E23)) | F24: =IF(SUM(F10:F23)=0,"",SUM(F10:F23)) | G24: =IF(SUM(G10:G23)=0,"",SUM(G10:G23)) | H24: =SUMPRODUCT($D$7:$G$7,D24:G24) | M24: not priced | N24: Order guide +10% = 1,659.0
A25: 4B Architraves (NRM2 22 / package JOI)
B26: Per face = 2 legs x 2150 + (door gap + 2 x 70). Internal doors both faces; external doors inside face only (bifold heads / jambs may be plastered - confirm).
A27: 4B.1 | B27: Architrave to internal doors, both faces, 18 x 69 (profile by the client) | C27: m | D27: 168.48 | E27: 252.72 | F27: 252.72 | G27: 63.48 | H27: =SUMPRODUCT($D$7:$G$7,D27:G27) | K27: =N(H27)*N(I27) | L27: =N(H27)*N(J27) | M27: =K27+L27 | N27: Order guide +10% = 1,622.3
A28: 4B.2 | B28: Architrave to external doors (front door and bifolds), inside face | C28: m | D28: 25.2 | E28: 37.8 | F28: 37.8 | G28: 19.65 | H28: =SUMPRODUCT($D$7:$G$7,D28:G28) | K28: =N(H28)*N(I28) | L28: =N(H28)*N(J28) | M28: =K28+L28 | N28: Order guide +10% = 265.0
A29: 4C Window boards (NRM2 22 / package JOI)
B30: Length = structural opening width + 2 x 50 horns; depth = internal reveal 195 + 25 nosing = 220 mm (order 225 mm MDF / uPVC).
A31: 4C.1 | B31: Window board 225 x 1,810 mm long, with horns, nosing to the front edge | C31: nr | D31: 4 | E31: 6 | F31: 6 | G31: 3 | H31: =SUMPRODUCT($D$7:$G$7,D31:G31) | K31: =N(H31)*N(I31) | L31: =N(H31)*N(J31) | M31: =K31+L31
A32: 4C.2 | B32: Window board 225 x 1,210 mm long, with horns, nosing to the front edge | C32: nr | D32: 6 | E32: 9 | F32: 9 | G32: 1 | H32: =SUMPRODUCT($D$7:$G$7,D32:G32) | K32: =N(H32)*N(I32) | L32: =N(H32)*N(J32) | M32: =K32+L32
A33: 4C.3 | B33: Window board 225 x 610 mm long, with horns, nosing to the front edge | C33: nr | D33: 2 | E33: 3 | F33: 3 | H33: =SUMPRODUCT($D$7:$G$7,D33:G33) | K33: =N(H33)*N(I33) | L33: =N(H33)*N(J33) | M33: =K33+L33
A34: 4C.T | B34: Window boards - total length | C34: m | D34: 15.72 | E34: 23.58 | F34: 23.58 | G34: 6.64 | H34: =SUMPRODUCT($D$7:$G$7,D34:G34) | M34: not priced | N34: Order guide +10% = 152.9
A35: 4D Loft access (NRM2 22 / package JOI)
A36: 4D.1 | B36: Loft access hatch, insulated and draught-sealed, 600 x 600 clear between trusses (trimming by the truss designer), with ladder if required | C36: nr | D36: 2 | E36: 3 | F36: 3 | G36: 1 | H36: =SUMPRODUCT($D$7:$G$7,D36:G36) | K36: =N(H36)*N(I36) | L36: =N(H36)*N(J36) | M36: =K36+L36 | N36: One per dwelling; position to suit the truss layout - confirm
A38: PACKAGE SUMMARY - Bill 4 Joinery - Skirtings, Architraves, Window Boards & Loft Hatches (package JOI; amounts by others, excl. VAT)
A39: Section | B39: Description | K39: Supply £ | L39: Install £ | M39: Total £
A40: 4A | B40: Skirtings (NRM2 22 / package JOI) | K40: =SUM(K9:K24) | L40: =SUM(L9:L24) | M40: =SUM(M9:M24)
A41: 4B | B41: Architraves (NRM2 22 / package JOI) | K41: =SUM(K26:K28) | L41: =SUM(L26:L28) | M41: =SUM(M26:M28)
A42: 4C | B42: Window boards (NRM2 22 / package JOI) | K42: =SUM(K30:K34) | L42: =SUM(L30:L34) | M42: =SUM(M30:M34)
A43: 4D | B43: Loft access (NRM2 22 / package JOI) | K43: =SUM(K36:K36) | L43: =SUM(L36:L36) | M43: =SUM(M36:M36)
A44: PACKAGE TOTAL - Bill 4, carried to the Cover overview | K44: =SUM(K40:K43) | L44: =SUM(L40:L43) | M44: =SUM(M40:M43)
A45: Pale-yellow cells are the only inputs (Supply rate, Install rate). Amounts, subtotals and totals are formulas; the sheet is protected without a password (Review > Unprotect Sheet). Amounts exclude VAT and are NOT part of the Nudura ICF price.

Sheet Bill 5 Partitions
C1: Bill 5 - Timber Stud Partitions - Framing, Openings, Pattresses & Fixings
C2: Non-loadbearing 38 x 89 C16 timber stud partitions from the TLSTF models (232 walls, 496.9 m, 140 door openings site-wide). Linings are in Bill 2, doorsets in Bill 3. [NRM2 16 / package JOI]
A4: DISCLAIMER: This information is supplied in good faith for guidance and coordination only. It is not part of the Nudura ICF price and must be checked and verified by the appropriate professional (quantity surveyor, designer, engineer or supplier) before use. Only the Nudura ICF formwork and associated accessories are included in our price. Quantities are measured from the quotation models and the SK11A drawings (DRAFT); no allowance for waste is included unless stated. Quantities are per block for each block type; the Site total multiplies by the number of blocks. Rates and amounts are by others.
A6: Ref | B6: Description | C6: Unit | D6: T01_SEMI per block | E6: T01_TER3 brick per block | F6: T01_TER3 stone per block | G6: T02_BUNG per block | H6: Site total qty | I6: Supply rate £ | J6: Install rate £ | K6: Supply £ | L6: Install £ | M6: Line total £ | N6: Notes
B7: Number of blocks of each type (Site total = per-block qty x blocks) | D7: 2 | E7: 3 | F7: 1 | G7: 2 | H7: =SUM(D7:G7) | N7: Blocks: T01_SEMI = B01, B04 (plots 01-02, 09-10); T01_TER3 brick = B02, B03, B05 (plots 03-08, 11-13); T01_TER3 stone = B08 (plots 16-18); T02_BUNG = B06, B07 (plots 14, 15)
A8: 5A Timber stud partitions, non-loadbearing - framing (NRM2 16 / package JOI)
B9: C16 softwood stud partitions as built in the TLSTF model (232 walls site-wide, all 38 x 89 per the SK11A thin walls): studs, head and bottom rails, mid-height noggins. Measured on the wall centre line, length x full height per level (HT01 GF 2,425; HT01 FF 2,670; HT02 2,336), gross - door openings NOT deducted (forming openings is measured in 5C). Rate 5A per m2 for framing LABOUR; enter a 5A Supply rate only when pricing a composite m2 rate - otherwise price timber supply in 5B, not both. Plasterboard, tape and skim are in Bill 2.
A10: 5A.1 | B10: HT01 ground floor partitions, 2,425 high: 38 x 89 C16 studs at 600 c/c, 38 x 89 head and bottom rails (general partitions) | C10: m2 | D10: 15.335 | E10: 23.034 | F10: 23.034 | H10: =SUMPRODUCT($D$7:$G$7,D10:G10) | K10: =N(H10)*N(I10) | L10: =N(H10)*N(J10) | M10: =K10+L10 | N10: HT01 GF: wall length x 2.425 m
A11: 5A.2 | B11: HT01 ground floor partitions, 2,425 high: 38 x 89 C16 studs at 400 c/c, 38 x 89 rails (bathroom / WC walls, pattressed) | C11: m2 | D11: 15.502 | E11: 23.284 | F11: 23.284 | H11: =SUMPRODUCT($D$7:$G$7,D11:G11) | K11: =N(H11)*N(I11) | L11: =N(H11)*N(J11) | M11: =K11+L11 | N11: HT01 GF: wall length x 2.425 m
A12: 5A.3 | B12: HT01 first floor partitions, 2,670 high: 38 x 89 C16 studs at 600 c/c, 38 x 89 head and bottom rails (general partitions) | C12: m2 | D12: 72.602 | E12: 108.971 | F12: 108.971 | H12: =SUMPRODUCT($D$7:$G$7,D12:G12) | K12: =N(H12)*N(I12) | L12: =N(H12)*N(J12) | M12: =K12+L12 | N12: HT01 FF: wall length x 2.670 m
A13: 5A.4 | B13: HT01 first floor partitions, 2,670 high: 38 x 89 C16 studs at 400 c/c, 38 x 89 rails (bathroom / WC walls, pattressed) | C13: m2 | D13: 41.817 | E13: 62.759 | F13: 62.759 | H13: =SUMPRODUCT($D$7:$G$7,D13:G13) | K13: =N(H13)*N(I13) | L13: =N(H13)*N(J13) | M13: =K13+L13 | N13: HT01 FF: wall length x 2.670 m
A14: 5A.5 | B14: HT02 ground floor partitions, 2,336 high: 38 x 89 C16 studs at 600 c/c, 38 x 89 head and bottom rails (general partitions) | C14: m2 | G14: 39.628 | H14: =SUMPRODUCT($D$7:$G$7,D14:G14) | K14: =N(H14)*N(I14) | L14: =N(H14)*N(J14) | M14: =K14+L14 | N14: HT02 GF: wall length x 2.336 m
A15: 5A.6 | B15: HT02 ground floor partitions, 2,336 high: 38 x 89 C16 studs at 400 c/c, 38 x 89 rails (bathroom / WC walls, pattressed) | C15: m2 | G15: 21.255 | H15: =SUMPRODUCT($D$7:$G$7,D15:G15) | K15: =N(H15)*N(I15) | L15: =N(H15)*N(J15) | M15: =K15+L15 | N15: HT02 GF: wall length x 2.336 m
A16: 5B Partition timber - supply (NRM2 16 / package JOI)
B17: ESTIMATE in linear metres of 38 x 89 C16 kiln-dried sawn softwood: common studs from the TLSTF build reports (WDP2_verify stud counts) x stud length, 2 king studs and cripples per door, head rail, bottom rail (less door gaps), door head rails and one mid-height noggin row. The TLSTF construction extract (cut lengths) was NOT exported for ES26-080 - reconcile against it before ordering. Supply only - labour in 5A / 5C.
A18: 5B.1 | B18: 38 x 89 C16 kiln-dried sawn softwood: studs, king studs and cripples over door heads | C18: m | D18: 489.016 | E18: 736.156 | F18: 736.156 | G18: 191.316 | H18: =SUMPRODUCT($D$7:$G$7,D18:G18) | K18: =N(H18)*N(I18) | L18: =N(H18)*N(J18) | M18: =K18+L18 | N18: Estimate - see 5B note
A19: 5B.2 | B19: 38 x 89 C16 kiln-dried sawn softwood: head and bottom rails, incl. door head rails | C19: m | D19: 111.14 | E19: 166.837 | F19: 166.837 | G19: 52.126 | H19: =SUMPRODUCT($D$7:$G$7,D19:G19) | K19: =N(H19)*N(I19) | L19: =N(H19)*N(J19) | M19: =K19+L19 | N19: Estimate - see 5B note
A20: 5B.3 | B20: 38 x 89 C16 kiln-dried sawn softwood: noggins (mid-height, fixing and board support) | C20: m | D20: 42.37 | E20: 63.619 | F20: 63.619 | G20: 20.963 | H20: =SUMPRODUCT($D$7:$G$7,D20:G20) | K20: =N(H20)*N(I20) | L20: =N(H20)*N(J20) | M20: =K20+L20 | N20: Estimate - see 5B note
A21: 5B.4 | B21: 38 x 89 C16 - 4.8 m lengths to order (run +5%, not cut-optimised) | C21: nr | D21: 141 | E21: 212 | F21: 212 | G21: 58 | H21: =SUMPRODUCT($D$7:$G$7,D21:G21) | M21: not priced | N21: Ordering guide only - not priced in addition to the runs above
A22: 5C Forming door openings in partitions (NRM2 16 / package JOI)
B23: Per opening: 2 full-height king studs, 38 x 89 head rail at 2,100 above the floor, cripple studs over the head and the bottom rail cut out across the gap. Timber is in 5B; the rate is per opening (labour; supply only for extra fixings / packers).
A24: 5C.1 | B24: Form door opening 700 wide x 2,100 high in 89 partition (cupboard / store): 2 king studs, head rail, cripples over | C24: nr | D24: 6 | E24: 9 | F24: 9 | H24: =SUMPRODUCT($D$7:$G$7,D24:G24) | K24: =N(H24)*N(I24) | L24: =N(H24)*N(J24) | M24: =K24+L24 | N24: Doorsets in Bill 3
A25: 5C.2 | B25: Form door opening 800 wide x 2,100 high in 89 partition (store / cupboard (HT02)): 2 king studs, head rail, cripples over | C25: nr | G25: 3 | H25: =SUMPRODUCT($D$7:$G$7,D25:G25) | K25: =N(H25)*N(I25) | L25: =N(H25)*N(J25) | M25: =K25+L25 | N25: Doorsets in Bill 3
A26: 5C.3 | B26: Form door opening 900 wide x 2,100 high in 89 partition (room / bathroom door): 2 king studs, head rail, cripples over | C26: nr | D26: 10 | E26: 15 | F26: 15 | G26: 3 | H26: =SUMPRODUCT($D$7:$G$7,D26:G26) | K26: =N(H26)*N(I26) | L26: =N(H26)*N(J26) | M26: =K26+L26 | N26: Doorsets in Bill 3
A27: 5D Pattresses, noggins to floor and roof structure, head restraint (NRM2 16 / package JOI)
B28: From the WDP2 partition build reports. Pattress: 18 mm WBP plywood between studs on the wet-room face of the 400 c/c walls, 150-1,950 above the floor, for sanitaryware and fittings (area = WDP2 pieces x 362 clear bay x 0.9 m - two pieces per bay, split at the noggin). Floor noggins between the PS10 metal-web joists where an HT01 partition runs parallel to them. Ceiling noggins between truss bottom chords where a top-floor partition runs parallel; slotted head-restraint clips allow truss deflection.
A29: 5D.1 | B29: 18 mm WBP plywood pattress boards between studs, wet-room face, cut to fit (band 150-1,950 above floor) | C29: m2 | D29: 16.29 | E29: 24.761 | F29: 24.761 | G29: 9.774 | H29: =SUMPRODUCT($D$7:$G$7,D29:G29) | K29: =N(H29)*N(I29) | L29: =N(H29)*N(J29) | M29: =K29+L29 | N29: Pieces per block: SEMI 50, TER3B 76, BUNG 30
A30: 5D.2 | B30: Noggins 47 x 250 C24 x ~301 long between FF joists over GF / FF partitions running parallel, skew-nailed or on hangers | C30: nr | D30: 10 | E30: 15 | F30: 15 | H30: =SUMPRODUCT($D$7:$G$7,D30:G30) | K30: =N(H30)*N(I30) | L30: =N(H30)*N(J30) | M30: =K30+L30 | N30: HT01 only. 15 partition lines per site model reported a BLOCKER (line on / beside a doubled trimmer) - detail by the floor designer
A31: 5D.3 | B31: Ceiling noggins, C24, depth to the truss bottom chord (97 HT01 / 72 HT02) x ~565 / ~490 long between chords over parallel partitions | C31: nr | D31: 54 | E31: 81 | F31: 81 | G31: 26 | H31: =SUMPRODUCT($D$7:$G$7,D31:G31) | K31: =N(H31)*N(I31) | L31: =N(H31)*N(J31) | M31: =K31+L31 | N31: HT02: 6 partition ends reported without a chord pair (blockers) - detail with the truss designer
A32: 5D.4 | B32: Partition head-restraint clip, slotted (Simpson Strong-Tie STC or UK equivalent - confirm), top-floor head rail to truss chord / noggin | C32: nr | D32: 92 | E32: 138 | F32: 138 | G32: 35 | H32: =SUMPRODUCT($D$7:$G$7,D32:G32) | K32: =N(H32)*N(I32) | L32: =N(H32)*N(J32) | M32: =K32+L32 | N32: 5 mm deflection gap kept at the head
A33: 5E Fixings and sundries (NRM2 16 / package JOI)
B34: Bottom rail fixings measured along the rail length (door gaps excluded). Fixing types are proposals - confirm with the designer.
A35: 5E.1 | B35: Fix GF bottom rails to the screeded ground-bearing slab: concrete screws or shot-fired fixings at max 600 c/c, on DPC strip (confirm) | C35: m | D35: 9.516 | E35: 14.3 | F35: 14.3 | G35: 20.963 | H35: =SUMPRODUCT($D$7:$G$7,D35:G35) | K35: =N(H35)*N(I35) | L35: =N(H35)*N(J35) | M35: =K35+L35 | N35: GF bottom rail length
A36: 5E.2 | B36: Fix HT01 FF bottom rails through the deck into joists / floor noggins | C36: m | D36: 32.854 | E36: 49.319 | F36: 49.319 | H36: =SUMPRODUCT($D$7:$G$7,D36:G36) | K36: =N(H36)*N(I36) | L36: =N(H36)*N(J36) | M36: =K36+L36 | N36: FF bottom rail length
A37: 5E.3 | B37: Head rail fixings: HT01 GF heads to joist bottom chords / floor noggins; top-floor heads via the 5D.4 clips | C37: item | K37: =IF(ISNUMBER(H37),H37,1)*N(I37) | L37: =IF(ISNUMBER(H37),H37,1)*N(J37) | M37: =K37+L37 | N37: Lump sum - the rate entered is the amount. Labour and fixings
A38: 5E.4 | B38: Nails, screws, framing fixings and sundries for the partition framing | C38: item | K38: =IF(ISNUMBER(H38),H38,1)*N(I38) | L38: =IF(ISNUMBER(H38),H38,1)*N(J38) | M38: =K38+L38 | N38: Lump sum - the rate entered is the amount.
A40: PACKAGE SUMMARY - Bill 5 Timber Stud Partitions - Framing, Openings, Pattresses & Fixings (package JOI; amounts by others, excl. VAT)
A41: Section | B41: Description | K41: Supply £ | L41: Install £ | M41: Total £
A42: 5A | B42: Timber stud partitions, non-loadbearing - framing (NRM2 16 / package JOI) | K42: =SUM(K9:K15) | L42: =SUM(L9:L15) | M42: =SUM(M9:M15)
A43: 5B | B43: Partition timber - supply (NRM2 16 / package JOI) | K43: =SUM(K17:K21) | L43: =SUM(L17:L21) | M43: =SUM(M17:M21)
A44: 5C | B44: Forming door openings in partitions (NRM2 16 / package JOI) | K44: =SUM(K23:K26) | L44: =SUM(L23:L26) | M44: =SUM(M23:M26)
A45: 5D | B45: Pattresses, noggins to floor and roof structure, head restraint (NRM2 16 / package JOI) | K45: =SUM(K28:K32) | L45: =SUM(L28:L32) | M45: =SUM(M28:M32)
A46: 5E | B46: Fixings and sundries (NRM2 16 / package JOI) | K46: =SUM(K34:K38) | L46: =SUM(L34:L38) | M46: =SUM(M34:M38)
A47: PACKAGE TOTAL - Bill 5, carried to the Cover overview | K47: =SUM(K42:K46) | L47: =SUM(L42:L46) | M47: =SUM(M42:M46)
A48: Pale-yellow cells are the only inputs (Supply rate, Install rate). Amounts, subtotals and totals are formulas; the sheet is protected without a password (Review > Unprotect Sheet). Amounts exclude VAT and are NOT part of the Nudura ICF price.

Sheet Schedule A Floor Areas
C1: Schedule A - Floor Areas by Room
C2: Per dwelling, measured on the finished faces of the model set-out (ICF on the drawn outer face). Not priced.
A4: DISCLAIMER: This information is supplied in good faith for guidance and coordination only. It is not part of the Nudura ICF price and must be checked and verified by the appropriate professional (quantity surveyor, designer, engineer or supplier) before use. Only the Nudura ICF formwork and associated accessories are included in our price. Quantities are measured from the quotation models and the SK11A drawings (DRAFT); no allowance for waste is included unless stated. Quantities are per block for each block type; the Site total multiplies by the number of blocks. Rates and amounts are by others.
A6: House type | B6: Unit position | C6: Level | D6: Room | E6: Drawn m2 | F6: Floor m2 | G6: Ceiling m2
A7: HT01 | B7: end unit | C7: GF | D7: Living / kitchen / dining (open plan, incl. hall and stair) | F7: 44.9 | G7: 44.9
A8: HT01 | B8: end unit | C8: GF | D8: WC | F8: 2.2 | G8: 2.2
A9: HT01 | B9: end unit | C9: GF | D9: Under-stair store | F9: 1.83 | G9: 1.83
A10: HT01 | B10: end unit | C10: FF | D10: Bedroom 1 | E10: 12.65 | F10: 13.08 | G10: 13.08
A11: HT01 | B11: end unit | C11: FF | D11: Bedroom 2 | E11: 12.56 | F11: 12.99 | G11: 12.99
A12: HT01 | B12: end unit | C12: FF | D12: Bedroom 3 | E12: 8.37 | F12: 8.67 | G12: 8.67
A13: HT01 | B13: end unit | C13: FF | D13: Landing (incl. stair well) | F13: 4.16 | G13: 6.92
A14: HT01 | B14: end unit | C14: FF | D14: Bathroom | E14: 3.72 | F14: 3.89 | G14: 3.89
A15: HT01 | B15: end unit | C15: FF | D15: Cupboard / store | F15: 0.9 | G15: 0.9
A16: HT01 | B16: end unit | C16: FF | D16: Cupboard / store | F16: 0.74 | G16: 0.74
A17: HT01 | B17: mid-terrace unit | C17: GF | D17: Living / kitchen / dining (open plan, incl. hall and stair) | F17: 44.96 | G17: 44.96
A18: HT01 | B18: mid-terrace unit | C18: GF | D18: WC | F18: 2.22 | G18: 2.22
A19: HT01 | B19: mid-terrace unit | C19: GF | D19: Under-stair store | F19: 1.86 | G19: 1.86
A20: HT01 | B20: mid-terrace unit | C20: FF | D20: Bedroom 1 | E20: 12.65 | F20: 13.08 | G20: 13.08
A21: HT01 | B21: mid-terrace unit | C21: FF | D21: Bedroom 2 | E21: 12.56 | F21: 12.99 | G21: 12.99
A22: HT01 | B22: mid-terrace unit | C22: FF | D22: Bedroom 3 | E22: 8.37 | F22: 8.71 | G22: 8.71
A23: HT01 | B23: mid-terrace unit | C23: FF | D23: Landing (incl. stair well) | F23: 4.19 | G23: 6.95
A24: HT01 | B24: mid-terrace unit | C24: FF | D24: Bathroom | E24: 3.72 | F24: 3.91 | G24: 3.91
A25: HT01 | B25: mid-terrace unit | C25: FF | D25: Cupboard / store | F25: 0.9 | G25: 0.9
A26: HT01 | B26: mid-terrace unit | C26: FF | D26: Cupboard / store | F26: 0.75 | G26: 0.75
A27: HT02 | B27: detached | C27: GF | D27: Kitchen / dining / living (open plan, incl. entrance hall) | E27: 40.69 | F27: 41.4 | G27: 41.4
A28: HT02 | B28: detached | C28: GF | D28: Bedroom 1 | E28: 10.64 | F28: 10.86 | G28: 10.86
A29: HT02 | B29: detached | C29: GF | D29: Bedroom 2 | E29: 10.57 | F29: 10.79 | G29: 10.79
A30: HT02 | B30: detached | C30: GF | D30: Bathroom | E30: 5.74 | F30: 5.81 | G30: 5.81
A31: HT02 | B31: detached | C31: GF | D31: Storage | E31: 0.85 | F31: 0.85 | G31: 0.85
A32: HT02 | B32: detached | C32: GF | D32: Storage | E32: 0.74 | F32: 0.72 | G32: 0.72
A33: HT02 | B33: detached | C33: GF | D33: Storage | E33: 0.7 | F33: 0.7 | G33: 0.7
D34: Drawn GIFA: HT01 96.5 m2, HT02 72.5 m2 (gross internal incl. walls); floor areas exclude the stair well.

Sheet Schedule B Openings
C1: Schedule B - Structural Opening Schedule (per block type)
C2: From the type specs. Sill and head from FFL 0. Not priced.
A4: DISCLAIMER: This information is supplied in good faith for guidance and coordination only. It is not part of the Nudura ICF price and must be checked and verified by the appropriate professional (quantity surveyor, designer, engineer or supplier) before use. Only the Nudura ICF formwork and associated accessories are included in our price. Quantities are measured from the quotation models and the SK11A drawings (DRAFT); no allowance for waste is included unless stated. Quantities are per block for each block type; the Site total multiplies by the number of blocks. Rates and amounts are by others.
A6: Block type | B6: Ref | C6: Level | D6: Face | E6: Type | F6: W mm | G6: H mm | H6: Sill mm | I6: Head mm | J6: Note
A7: T01_SEMI | B7: U1-L1-F01 | C7: GF | D7: Front | E7: window | F7: 510 | G7: 1050 | H7: 1050 | I7: 2100 | J7: GF WC window
A8: T01_SEMI | B8: U1-L1-F02 | C8: GF | D8: Front | E8: door | F8: 1110 | G8: 2100 | H8: 0 | I8: 2100 | J8: GF front entrance door
A9: T01_SEMI | B9: U1-L1-F03 | C9: GF | D9: Front | E9: window | F9: 1710 | G9: 1050 | H9: 1050 | I9: 2100 | J9: GF living window (3-light)
A10: T01_SEMI | B10: U1-L1-R04 | C10: GF | D10: Rear | E10: door | F10: 2610 | G10: 2100 | H10: 0 | I10: 2100 | J10: GF kitchen/dining bifold (3-leaf)
A11: T01_SEMI | B11: U1-L2-F05 | C11: FF | D11: Front | E11: window | F11: 1110 | G11: 1050 | H11: 3750 | I11: 4800 | J11: FF bathroom window
A12: T01_SEMI | B12: U1-L2-F06 | C12: FF | D12: Front | E12: window | F12: 1710 | G12: 1200 | H12: 3600 | I12: 4800 | J12: FF bedroom 1 window (3-light)
A13: T01_SEMI | B13: U1-L2-R07 | C13: FF | D13: Rear | E13: window | F13: 1110 | G13: 1200 | H13: 3600 | I13: 4800 | J13: FF bedroom 3 window
A14: T01_SEMI | B14: U1-L2-R08 | C14: FF | D14: Rear | E14: window | F14: 1110 | G14: 1200 | H14: 3600 | I14: 4800 | J14: FF bedroom 2 window
A15: T01_SEMI | B15: U2-L1-F01 | C15: GF | D15: Front | E15: window | F15: 510 | G15: 1050 | H15: 1050 | I15: 2100 | J15: GF WC window
A16: T01_SEMI | B16: U2-L1-F02 | C16: GF | D16: Front | E16: door | F16: 1110 | G16: 2100 | H16: 0 | I16: 2100 | J16: GF front entrance door
A17: T01_SEMI | B17: U2-L1-F03 | C17: GF | D17: Front | E17: window | F17: 1710 | G17: 1050 | H17: 1050 | I17: 2100 | J17: GF living window (3-light)
A18: T01_SEMI | B18: U2-L1-R04 | C18: GF | D18: Rear | E18: door | F18: 2610 | G18: 2100 | H18: 0 | I18: 2100 | J18: GF kitchen/dining bifold (3-leaf)
... A53: T02_BUNG | B53: U1-L1-R07 | C53: GF | D53: Rear | E53: door | F53: 2610 | G53: 2100 | H53: 0 | I53: 2100 | J53: living bifold 2
A55: Site: T01_SEMI 16 x 2 + T01_TER3 24 x 4 + T02_BUNG 7 x 2 = 142 openings

Sheet Schedule C Per Plot
C1: Schedule C - Key Quantities per Plot
C2: Per dwelling (plots 01-18). Reference only - the bills carry the priced quantities. Not priced.
A4: DISCLAIMER: This information is supplied in good faith for guidance and coordination only. It is not part of the Nudura ICF price and must be checked and verified by the appropriate professional (quantity surveyor, designer, engineer or supplier) before use. Only the Nudura ICF formwork and associated accessories are included in our price. Quantities are measured from the quotation models and the SK11A drawings (DRAFT); no allowance for waste is included unless stated. Quantities are per block for each block type; the Site total multiplies by the number of blocks. Rates and amounts are by others.
A6: Plot | B6: Block | C6: Block type | D6: Unit | E6: Position | F6: Facing | G6: Slips walls m2 | H6: PB walls m2 | I6: PB ceilings m2 | J6: Doors nr | K6: Skirting m | L6: Partitions m2
A7: 01 | B7: B01 | C7: T01_SEMI | D7: U1 | E7: end | F7: brick | G7: 117.28 | H7: 254.89 | I7: 97.72 | J7: 8 | K7: 86.25 | L7: 72.63
A8: 02 | B8: B01 | C8: T01_SEMI | D8: U2 | E8: end | F8: brick | G8: 117.28 | H8: 254.89 | I8: 97.72 | J8: 8 | K8: 86.25 | L8: 72.63
A9: 03 | B9: B02 | C9: T01_TER3 | D9: U1 | E9: end | F9: brick | G9: 117.28 | H9: 254.89 | I9: 97.72 | J9: 8 | K9: 86.25 | L9: 72.63
A10: 04 | B10: B02 | C10: T01_TER3 | D10: U2 | E10: mid | F10: brick | G10: 46.06 | H10: 255.41 | I10: 97.95 | J10: 8 | K10: 86.45 | L10: 72.79
A11: 05 | B11: B02 | C11: T01_TER3 | D11: U3 | E11: end | F11: brick | G11: 117.28 | H11: 254.89 | I11: 97.72 | J11: 8 | K11: 86.25 | L11: 72.63
A12: 06 | B12: B03 | C12: T01_TER3 | D12: U1 | E12: end | F12: brick | G12: 117.28 | H12: 254.89 | I12: 97.72 | J12: 8 | K12: 86.25 | L12: 72.63
A13: 07 | B13: B03 | C13: T01_TER3 | D13: U2 | E13: mid | F13: brick | G13: 46.06 | H13: 255.41 | I13: 97.95 | J13: 8 | K13: 86.45 | L13: 72.79
A14: 08 | B14: B03 | C14: T01_TER3 | D14: U3 | E14: end | F14: brick | G14: 117.28 | H14: 254.89 | I14: 97.72 | J14: 8 | K14: 86.25 | L14: 72.63
A15: 09 | B15: B04 | C15: T01_SEMI | D15: U1 | E15: end | F15: brick | G15: 117.28 | H15: 254.89 | I15: 97.72 | J15: 8 | K15: 86.25 | L15: 72.63
A16: 10 | B16: B04 | C16: T01_SEMI | D16: U2 | E16: end | F16: brick | G16: 117.28 | H16: 254.89 | I16: 97.72 | J16: 8 | K16: 86.25 | L16: 72.63
A17: 11 | B17: B05 | C17: T01_TER3 | D17: U1 | E17: end | F17: brick | G17: 117.28 | H17: 254.89 | I17: 97.72 | J17: 8 | K17: 86.25 | L17: 72.63
A18: 12 | B18: B05 | C18: T01_TER3 | D18: U2 | E18: mid | F18: brick | G18: 46.06 | H18: 255.41 | I18: 97.95 | J18: 8 | K18: 86.45 | L18: 72.79
... A24: 18 | B24: B08 | C24: T01_TER3 | D24: U1 | E24: end | F24: stone | G24: 117.28 | H24: 254.89 | I24: 97.72 | J24: 8 | K24: 86.25 | L24: 72.63
A25: Total | G25: =SUM(G7:G24) | H25: =SUM(H7:H24) | I25: =SUM(I7:I24) | J25: =SUM(J7:J24) | K25: =SUM(K7:K24) | L25: =SUM(L7:L24)

Sheet Schedule D Sloping Plots
C1: Schedule D - Sloping Plots: exposure at DPC (provisional)
C2: Existing survey corner levels (10G); FFL = mean corner ground + 150. Not priced.
A4: DISCLAIMER: This information is supplied in good faith for guidance and coordination only. It is not part of the Nudura ICF price and must be checked and verified by the appropriate professional (quantity surveyor, designer, engineer or supplier) before use. Only the Nudura ICF formwork and associated accessories are included in our price. Quantities are measured from the quotation models and the SK11A drawings (DRAFT); no allowance for waste is included unless stated. Quantities are per block for each block type; the Site total multiplies by the number of blocks. Rates and amounts are by others.
A6: Block | B6: Type | C6: FFL AOD | D6: Fall mm | E6: Exposed below DPC m2 | F6: Ground above DPC m2 | G6: Note
A7: B01 | B7: T01_SEMI | C7: 201.84 | D7: 1750 | E7: 9.72 | F7: 9.72 | G7: brick
A8: B02 | B8: T01_TER3 | C8: 203.18 | D8: 1220 | E8: 8.88 | F8: 8.88 | G8: brick
A9: B03 | B9: T01_TER3 | C9: 204.528 | D9: 2230 | E9: 15.09 | F9: 15.09 | G9: brick
A10: B04 | B10: T01_SEMI | C10: 206.69 | D10: 370 | E10: 2.68 | F10: 2.68 | G10: brick
A11: B05 | B11: T01_TER3 | C11: 204.445 | D11: 2250 | E11: 16.41 | F11: 16.41 | G11: brick
A12: B06 | B12: T02_BUNG | C12: 201.86 | D12: 1120 | E12: 6.14 | F12: 6.14 | G12: brick
A13: B07 | B13: T02_BUNG | C13: 200.028 | D13: 1620 | E13: 9.48 | F13: 9.48 | G13: brick
A14: B08 | B14: T01_TER3 | C14: 198.053 | D14: 2080 | E14: 14.91 | F14: 14.91 | G14: stone
